Workbook

Sheet Resumão Geral
C3: Período | D3: Janeiro | E3: Fevereiro | F3: março | G3: abril | H3: maio | I3: junho | J3: julho | K3: agosto | L3: setembro | M3: outubro | N3: novembro | O3: dezembro
C5: Fontes de Receita (+) | D5: =SUM(D8,D14,D18,D22) -> 143250.9 | E5: =SUM(E8,E14,E18,E22) -> 143599.21 | F5: =SUM(F8,F14,F18,F22) -> 157197.52 | G5: =SUM(G8,G14,G18,G22) -> 170282.82 | H5: =SUM(H8,H14,H18,H22) -> 183685.6 | I5: =SUM(I8,I14,I18,I22) -> 223105.87 | J5: =SUM(J8,J14,J18,J22) -> 258553.33 | K5: =SUM(K8,K14,K18,K22) -> 286372 | ... O5: =SUM(O8,O14,O18,O22) -> 345814.67
C6: Quantidada de Projetos Fechados Consultoria | D6: ='Projeção Biel Ajustada'!E11 -> 8 | E6: ='Projeção Biel Ajustada'!F11 -> 9.6 | F6: ='Projeção Biel Ajustada'!G11 -> 12.8 | G6: ='Projeção Biel Ajustada'!H11 -> 14.08 | H6: ='Projeção Biel Ajustada'!I11 -> 15.36 | I6: ='Projeção Biel Ajustada'!J11 -> 16.64 | J6: ='Projeção Biel Ajustada'!K11 -> 17.92 | K6: ='Projeção Biel Ajustada'!L11 -> 19.2 | ... O6: ='Projeção Biel Ajustada'!P11 -> 19.2 | T6: Resultado Anual 2026 - Projetado | W6: Flags | Y6: Valor Por Cliente
C7: Quantidada de Projetos Fechados Obra | D7: ='Projeção Biel Ajustada'!E84 -> 1.04 | E7: ='Projeção Biel Ajustada'!F84 -> 1.248 | F7: ='Projeção Biel Ajustada'!G84 -> 1.664 | G7: ='Projeção Biel Ajustada'!H84 -> 1.8304 | H7: ='Projeção Biel Ajustada'!I84 -> 1.9968 | I7: ='Projeção Biel Ajustada'!J84 -> 2.1632 | J7: ='Projeção Biel Ajustada'!K84 -> 2.3296 | K7: ='Projeção Biel Ajustada'!L84 -> 2.496 | ... O7: ='Projeção Biel Ajustada'!P84 -> 2.496 | T7: Receitas | U7: =SUM(D5:O5) -> 2910186.4 | W7: Reserva de Caixa | X7: =SUM(D60:O60) -> 122037.72 | Y7: =X7/SUM($D$6:$O$7) -> 557.8408
C8: Receita Base | D8: =SUM(D9:D12) -> 122640.83 | E8: =SUM(E9:E12) -> 95669.14 | F8: =SUM(F9:F12) -> 72840.79 | G8: =SUM(G9:G12) -> 42055.15 | H8: =SUM(H9:H12) -> 28208.8 | I8: =SUM(I9:I12) -> 28208.8 | J8: =SUM(J9:J12) -> 28208.8 | K8: =SUM(K9:K12) -> 28208.8 | ... O8: =SUM(O9:O12) -> 28208.8 | T8: CSP | U8: =SUM(D27:O27) -> 469432.13 | W8: Reserva de Brindes Clientes | X8: =SUM(D59:O59) -> 65106.088 | Y8: =X8/SUM($D$6:$O$7) -> 297.60334
C9: Assinaturas | D9: =5300+1097.8+1230+80+1000 -> 8707.8 | E9: =5300+1097.8+1230+80 -> 7707.8 | F9: =5300+1097.8+1230+80 -> 7707.8 | G9: =5300+1097.8+1230+80 -> 7707.8 | H9: =5300+1097.8+1230+80 -> 7707.8 | I9: =5300+1097.8+1230+80 -> 7707.8 | J9: =5300+1097.8+1230+80 -> 7707.8 | K9: =5300+1097.8+1230+80 -> 7707.8 | L9: =5300+1097.8+1230+80 -> 7707.8 | ... O9: =5300+1097.8+1230+80 -> 7707.8 | T9: Lucro Bruto | U9: =U7-U8 -> 2440754.3 | W9: Reserva de Eventos | X9: =SUM(D58:O58) -> 32553.044 | Y9: =X9/SUM($D$6:$O$7) -> 148.80167
C10: Bra | D10: 20501 | E10: 20501 | F10: 20501 | G10: 20501 | H10: 20501 | I10: 20501 | J10: 20501 | K10: 20501 | L10: 20501 | M10: 20501 | N10: 20501 | O10: 20501 | T10: Margem Bruta | U10: =U9/U7 -> 0.83869345 | W10: Reserva de Brindes Membros | X10: =SUM(D57:O57) -> 10851.015 | Y10: =X10/SUM($D$6:$O$7) -> 49.600557
C11: Consultorias 2025 | D11: =59538.38+2250 -> 61788.38 | E11: =43916.69 -> 43916.69 | F11: 30263.33 | G11: 11173.35 | T11: Despesas | U11: =SUM(D45:O45) -> 1364604.9
C12: Obras 2025 | D12: =24893.65+6750 -> 31643.65 | E12: 23543.65 | F12: 14368.66 | G12: 2673 | T12: Lucro Operacional (Ebitda) | U12: =U9-U11 -> 1076149.4
T13: Margem Ebitda | U13: =U12/U7 -> 0.36978709 | W13: Meta de Contratos | X13: 1q | Y13: 2q | Z13: 3q | AA13: 4q | AB13: Total
C14: Consultoria | D14: =D15 -> 15843.4 | E14: =E15 -> 37443.4 | F14: =F15 -> 66243.4 | G14: =G15 -> 101443.4 | H14: =H15 -> 124000 | I14: =I15 -> 148160 | J14: =J15 -> 168640 | K14: =K15 -> 191040 | ... O14: =O15 -> 240000 | T14: Despesas Financeiras | U14: =SUM(D40:O43) -> 98420.222 | W14: Consultorias | X14: =SUM('Projeção Biel Ajustada'!E13:G13) -> 264973.6 | Y14: =SUM('Projeção Biel Ajustada'!H13:J13) -> 477440 | Z14: =SUM('Projeção Biel Ajustada'!K13:M13) -> 673280 | AA14: =SUM('Projeção Biel Ajustada'!N13:P13) -> 714240 | AB14: =SUM(X14:AA14) -> 2129933.6
C15: Vendas de Consultora | D15: ='Projeção Biel Ajustada'!E18 -> 15843.4 | E15: ='Projeção Biel Ajustada'!F18 -> 37443.4 | F15: ='Projeção Biel Ajustada'!G18 -> 66243.4 | G15: ='Projeção Biel Ajustada'!H18 -> 101443.4 | H15: ='Projeção Biel Ajustada'!I18 -> 124000 | I15: ='Projeção Biel Ajustada'!J18 -> 148160 | J15: ='Projeção Biel Ajustada'!K18 -> 168640 | K15: ='Projeção Biel Ajustada'!L18 -> 191040 | ... O15: ='Projeção Biel Ajustada'!P18 -> 240000 | T15: Impostos | U15: =SUM(D39:O39) -> 397296.53 | W15: Obras | X15: =SUM('Projeção Biel Ajustada'!E85:G85) -> 72453.333 | Y15: =SUM('Projeção Biel Ajustada'!H85:J85) -> 109824 | Z15: =SUM('Projeção Biel Ajustada'!K85:M85) -> 137280 | AA15: =SUM('Projeção Biel Ajustada'!N85:P85) -> 141856 | AB15: =SUM(X15:AA15) -> 461413.33
T16: Lucro Líquido | U16: =U12-SUM(U14:U15) -> 580432.63 | W16: Plataforma | Y16: =SUM(G23:I23) -> 1792 | Z16: =SUM(J23:L23) -> 5017.6 | AA16: =SUM(M23:O23) -> 8640 | AB16: =SUM(X16:AA16) -> 15449.6
T17: Margem Líquida | U17: =U16/U7 -> 0.19944861 | W17: Plataforma Ger. Carr | Y17: =SUM(I24) -> 332.8 | Z17: =SUM(J24:L24) -> 3251.2 | AA17: =SUM(M24:O24) -> 6873.6 | AB17: =SUM(X17:AA17) -> 10457.6
C18: Obras | D18: =D19 -> 4766.6667 | E18: =E19 -> 10486.667 | F18: =F19 -> 18113.333 | G18: =G19 -> 26502.667 | H18: =H19 -> 30888 | I18: =I19 -> 35082.667 | J18: =J19 -> 38133.333 | K18: =K19 -> 41184 | ... O18: =O19 -> 47666.667 | W18: Setup | Y18: ='Projeção Biel Ajustada'!J70 -> 20800 | Z18: =SUM('Projeção Biel Ajustada'!K70:M70) -> 72000 | AA18: =SUM('Projeção Biel Ajustada'!N70:P70) -> 74400 | AB18: =SUM(X18:AA18) -> 167200
C19: Vendas de Obras | D19: ='Projeção Biel Ajustada'!E90 -> 4766.6667 | E19: ='Projeção Biel Ajustada'!F90 -> 10486.667 | F19: ='Projeção Biel Ajustada'!G90 -> 18113.333 | G19: ='Projeção Biel Ajustada'!H90 -> 26502.667 | H19: ='Projeção Biel Ajustada'!I90 -> 30888 | I19: ='Projeção Biel Ajustada'!J90 -> 35082.667 | J19: ='Projeção Biel Ajustada'!K90 -> 38133.333 | K19: ='Projeção Biel Ajustada'!L90 -> 41184 | ... O19: ='Projeção Biel Ajustada'!P90 -> 47666.667 | W19: Total | X19: =SUM(X14:X18) -> 337426.93 | Y19: =SUM(Y14:Y18) -> 610188.8 | Z19: =SUM(Z14:Z18) -> 890828.8 | AA19: =SUM(AA14:AA18) -> 946009.6 | AB19: =SUM(AB14:AB18) -> 2784454.1
C22: Plataforma | D22: =SUM(D23:D25) -> 0 | E22: =SUM(E23:E25) -> 0 | F22: =SUM(F23:F25) -> 0 | G22: =SUM(G23:G25) -> 281.6 | H22: =SUM(H23:H25) -> 588.8 | I22: =SUM(I23:I25) -> 11654.4 | J22: =SUM(J23:J25) -> 23571.2 | K22: =SUM(K23:K25) -> 25939.2 | ... O22: =SUM(O23:O25) -> 29939.2
C23: MRR Plataforma | G23: ='Projeção Biel Ajustada'!H60 -> 281.6 | H23: ='Projeção Biel Ajustada'!I60 -> 588.8 | I23: ='Projeção Biel Ajustada'!J60 -> 921.6 | J23: ='Projeção Biel Ajustada'!K60 -> 1280 | K23: ='Projeção Biel Ajustada'!L60 -> 1664 | L23: ='Projeção Biel Ajustada'!M60 -> 2073.6 | M23: ='Projeção Biel Ajustada'!N60 -> 2496 | N23: ='Projeção Biel Ajustada'!O60 -> 2880 | O23: ='Projeção Biel Ajustada'!P60 -> 3264
C24: MRR Plataforma de Geren. de Carr | I24: ='Projeção Biel Ajustada'!J68 -> 332.8 | J24: ='Projeção Biel Ajustada'!K68 -> 691.2 | K24: ='Projeção Biel Ajustada'!L68 -> 1075.2 | L24: ='Projeção Biel Ajustada'!M68 -> 1484.8 | M24: ='Projeção Biel Ajustada'!N68 -> 1907.2 | N24: ='Projeção Biel Ajustada'!O68 -> 2291.2 | O24: ='Projeção Biel Ajustada'!P68 -> 2675.2
C25: Setup | I25: ='Projeção Biel Ajustada'!J73 -> 10400 | J25: ='Projeção Biel Ajustada'!K73 -> 21600 | K25: ='Projeção Biel Ajustada'!L73 -> 23200 | L25: ='Projeção Biel Ajustada'!M73 -> 24800 | M25: ='Projeção Biel Ajustada'!N73 -> 26000 | N25: ='Projeção Biel Ajustada'!O73 -> 25200 | O25: ='Projeção Biel Ajustada'!P73 -> 24000
C27: Custos Operação (-) | D27: =SUM(D28:D33) -> 22949.737 | E27: =SUM(E28:E33) -> 24412.73 | F27: =SUM(F28:F33) -> 31955.065 | G27: =SUM(G28:G33) -> 32978.067 | H27: =SUM(H28:H33) -> 35165.6 | I27: =SUM(I28:I33) -> 39759.733 | J27: =SUM(J28:J33) -> 42625.867 | K27: =SUM(K28:K33) -> 46452 | ... O27: =SUM(O28:O33) -> 46452
C28: Comissão de Vendas | D28: ='Projeção Biel Ajustada'!E112 -> 2061.0067 | E28: ='Projeção Biel Ajustada'!F112 -> 2732 | F28: ='Projeção Biel Ajustada'!G112 -> 7285.3333 | G28: ='Projeção Biel Ajustada'!H112 -> 8717.8667 | H28: ='Projeção Biel Ajustada'!I112 -> 9510.4 | I28: ='Projeção Biel Ajustada'!J112 -> 12174.933 | J28: ='Projeção Biel Ajustada'!K112 -> 13111.467 | K28: ='Projeção Biel Ajustada'!L112 -> 15008 | ... O28: ='Projeção Biel Ajustada'!P112 -> 15008
C29: Materiais de Obras | D29: ='Projeção Biel Ajustada'!E91+(D12*20%) -> 14908.73 | E29: ='Projeção Biel Ajustada'!F91+(E12*20%) -> 15004.73 | F29: ='Projeção Biel Ajustada'!G91+(F12*20%) -> 16601.732 | G29: ='Projeção Biel Ajustada'!H91+(G12*20%) -> 15635.4 | H29: ='Projeção Biel Ajustada'!I91 -> 16473.6 | I29: ='Projeção Biel Ajustada'!J91 -> 17846.4 | J29: ='Projeção Biel Ajustada'!K91 -> 19219.2 | K29: ='Projeção Biel Ajustada'!L91 -> 20592 | L29: ='Projeção Biel Ajustada'!M91 -> 21964.8 | M29: ='Projeção Biel Ajustada'!N91 -> 22651.2 | N29: ='Projeção Biel Ajustada'!O91 -> 20592 | O29: ='Projeção Biel Ajustada'!P91 -> 20592
C30: Custos de Execução de Obras (Transporte e alimentação) | D30: ='Premissas gerais'!$B$126+'Premissas gerais'!$B$125 -> 2500 | E30: ='Premissas gerais'!$B$126+'Premissas gerais'!$B$125 -> 2500 | F30: ='Premissas gerais'!$B$126+'Premissas gerais'!$B$125 -> 2500 | G30: ='Premissas gerais'!$B$126+'Premissas gerais'!$B$125 -> 2500 | H30: ='Premissas gerais'!$B$126+'Premissas gerais'!$B$125 -> 2500 | I30: ='Premissas gerais'!$B$126+'Premissas gerais'!$B$125 -> 2500 | J30: ='Premissas gerais'!$B$126+'Premissas gerais'!$B$125 -> 2500 | K30: ='Premissas gerais'!$B$126+'Premissas gerais'!$B$125 -> 2500 | ... O30: ='Premissas gerais'!$B$126+'Premissas gerais'!$B$125 -> 2500
C31: Custo do Serviço Prestado Consult. | D31: ='Projeção Biel Ajustada'!E36 -> 3480 | E31: ='Projeção Biel Ajustada'!F36 -> 4176 | F31: ='Projeção Biel Ajustada'!G36 -> 5568 | G31: ='Projeção Biel Ajustada'!H36 -> 6124.8 | H31: ='Projeção Biel Ajustada'!I36 -> 6681.6 | I31: ='Projeção Biel Ajustada'!J36 -> 7238.4 | J31: ='Projeção Biel Ajustada'!K36 -> 7795.2 | K31: ='Projeção Biel Ajustada'!L36 -> 8352 | ... O31: ='Projeção Biel Ajustada'!P36 -> 8352
C32: Materiais de Consultoria
C34: Lucro Bruto | D34: =D5-D27 -> 120301.16 | E34: =E5-E27 -> 119186.48 | F34: =F5-F27 -> 125242.46 | G34: =G5-G27 -> 137304.75 | H34: =H5-H27 -> 148520 | I34: =I5-I27 -> 183346.13 | J34: =J5-J27 -> 215927.47 | K34: =K5-K27 -> 239920 | ... O34: =O5-O27 -> 299362.67
C35: Margem Bruta | D35: =D34/D5 -> 0.83979342 | E35: =E34/E5 -> 0.82999398 | F35: =F34/F5 -> 0.7967203 | G35: =G34/G5 -> 0.80633356 | H35: =H34/H5 -> 0.80855549 | I35: =I34/I5 -> 0.82178983 | J35: =J34/J5 -> 0.83513704 | K35: =K34/K5 -> 0.8377914 | ... O35: =O34/O5 -> 0.86567371
C37: Despesas Financeiras (-) | D37: =SUM(D39,D40,D41,D42,D43) -> 28964.88 | E37: =SUM(E39,E40,E41,E42,E43) -> 25993.252 | F37: =SUM(F39,F40,F41,F42,F43) -> 26403.297 | G37: =SUM(G39,G40,G41,G42,G43) -> 28625.376 | H37: =SUM(H39,H40,H41,H42,H43) -> 30811.531 | I37: =SUM(I39,I40,I41,I42,I43) -> 33082.136 | J37: =SUM(J39,J40,J41,J42,J43) -> 39040.924 | K37: =SUM(K39,K40,K41,K42,K43) -> 47275.175 | ... O37: =SUM(O39,O40,O41,O42,O43) -> 65331.508
C38: Alíquota Simples Nacional | D38: ='Premissas gerais'!N115 -> 0.12798836 | E38: ='Premissas gerais'!O115 -> 0.13016164 | F38: ='Premissas gerais'!P115 -> 0.13190586 | G38: ='Premissas gerais'!Q115 -> 0.13388971 | H38: ='Premissas gerais'!R115 -> 0.13574142 | I38: ='Premissas gerais'!S115 -> 0.13753829 | J38: ='Premissas gerais'!T115 -> 0.13939093 | K38: ='Premissas gerais'!U116 -> 0.14313122 | L38: ='Premissas gerais'!V116 -> 0.14905564 | M38: ='Premissas gerais'!W116 -> 0.15478651 | N38: ='Premissas gerais'!X116 -> 0.15948359 | O38: ='Premissas gerais'!Y116 -> 0.16385178
C39: Impostos sobre o Faturamento | D39: ='Premissas gerais'!M114*D38 -> 20242.64 | E39: =D5*E38 -> 18645.772 | F39: =E5*F38 -> 18941.577 | G39: =F5*G38 -> 21047.131 | H39: =G5*H38 -> 23114.431 | I39: =H5*I38 -> 25263.803 | J39: =I5*J38 -> 31098.935 | K39: =J5*K38 -> 37007.055 | L39: =K5*L38 -> 42685.361 | ... O39: =N5*O38 -> 56733.132
C40: INSS | D40: =11%*1621*4 -> 713.24 | E40: =11%*1621*8 -> 1426.48 | F40: =11%*1621*8 -> 1426.48 | G40: =11%*1621*8 -> 1426.48 | H40: =11%*1621*8 -> 1426.48 | I40: =11%*1621*8 -> 1426.48 | J40: =11%*1621*8 -> 1426.48 | K40: =11%*1621*8 -> 1426.48 | L40: =11%*1621*8 -> 1426.48 | ... O40: =11%*1621*8 -> 1426.48
C41: CIM | D41: 2200 | K41: 2200
C42: Pagamento do Empréstimo Caixa | D42: 5600 | E42: =D42*1.02 -> 5712 | F42: =E42*1.02 -> 5826.24 | G42: =F42*1.02 -> 5942.7648 | H42: =G42*1.02 -> 6061.6201 | I42: =H42*1.02 -> 6182.8525 | J42: =I42*1.02 -> 6306.5095 | K42: =J42*1.02 -> 6432.6397 | L42: =K42*1.02 -> 6561.2925 | ... O42: =N42*1.02 -> 6962.8961
C43: Tarifas Bancárias | D43: =69+70+70 -> 209 | E43: =69+70+70 -> 209 | F43: =69+70+70 -> 209 | G43: =69+70+70 -> 209 | H43: =69+70+70 -> 209 | I43: =69+70+70 -> 209 | J43: =69+70+70 -> 209 | K43: =69+70+70 -> 209 | ... O43: =69+70+70 -> 209
C45: Custos Fixos (-) | D45: =SUM(D47,D50,D54) -> 87355.07 | E45: =SUM(E47,E50,E54) -> 91948.019 | F45: =SUM(F47,F50,F54) -> 94486.535 | G45: =SUM(G47,G50,G54) -> 97511.329 | H45: =SUM(H47,H50,H54) -> 99664.576 | I45: =SUM(I47,I50,I54) -> 103329.18 | J45: =SUM(J47,J50,J54) -> 120600.61 | K45: =SUM(K47,K50,K54) -> 123462.32 | ... O45: =SUM(O47,O50,O54) -> 161201.01
C47: Escritório, Jurídico, Contábil e Outros | D47: =SUM(D48:D49) -> 9721 | E47: =SUM(E48:E49) -> 9721 | F47: =SUM(F48:F49) -> 9721 | G47: =SUM(G48:G49) -> 9721 | H47: =SUM(H48:H49) -> 9721 | I47: =SUM(I48:I49) -> 9721 | J47: =SUM(J48:J49) -> 9721 | K47: =SUM(K48:K49) -> 9721 | ... O47: =SUM(O48:O49) -> 9721
C48: Escritório (água, luz, internet, energia, infra. e copa) | D48: ='Premissas gerais'!$B$90 -> 7000 | E48: ='Premissas gerais'!$B$90 -> 7000 | F48: ='Premissas gerais'!$B$90 -> 7000 | G48: ='Premissas gerais'!$B$90 -> 7000 | H48: ='Premissas gerais'!$B$90 -> 7000 | I48: ='Premissas gerais'!$B$90 -> 7000 | J48: ='Premissas gerais'!$B$90 -> 7000 | K48: ='Premissas gerais'!$B$90 -> 7000 | ... O48: ='Premissas gerais'!$B$90 -> 7000
C49: Jurídico e Contábil | D49: ='Premissas gerais'!$B$94 -> 2721 | E49: ='Premissas gerais'!$B$94 -> 2721 | F49: ='Premissas gerais'!$B$94 -> 2721 | G49: ='Premissas gerais'!$B$94 -> 2721 | H49: ='Premissas gerais'!$B$94 -> 2721 | I49: ='Premissas gerais'!$B$94 -> 2721 | J49: ='Premissas gerais'!$B$94 -> 2721 | K49: ='Premissas gerais'!$B$94 -> 2721 | ... O49: ='Premissas gerais'!$B$94 -> 2721
C50: Custos Fixos Time + Marketing | D50: =SUM(D51:D53) -> 60960 | E50: =SUM(E51:E53) -> 59600 | F50: =SUM(F51:F53) -> 59600 | G50: =SUM(G51:G53) -> 59600 | H50: =SUM(H51:H53) -> 59600 | I50: =SUM(I51:I53) -> 59600 | J50: =SUM(J51:J53) -> 73600 | K50: =SUM(K51:K53) -> 73600 | ... O50: =SUM(O51:O53) -> 105000
C51: Equipe Base | D51: =SUM('Premissas gerais'!B63:B76,'Premissas gerais'!B82,'Premissas gerais'!B84:B87,'Premissas gerais'!B88)*1.2 -> 54960 | E51: =SUM('Premissas gerais'!$C$63:$C$75,'Premissas gerais'!$C$84:$C$87) -> 53600 | F51: =SUM('Premissas gerais'!$C$63:$C$75,'Premissas gerais'!$C$84:$C$87) -> 53600 | G51: =SUM('Premissas gerais'!$C$63:$C$75,'Premissas gerais'!$C$84:$C$87) -> 53600 | H51: =SUM('Premissas gerais'!$C$63:$C$75,'Premissas gerais'!$C$84:$C$87) -> 53600 | I51: =SUM('Premissas gerais'!$C$63:$C$75,'Premissas gerais'!$C$84:$C$87) -> 53600 | J51: =SUM('Premissas gerais'!$D$63:$D$75,'Premissas gerais'!$D$81,'Premissas gerais'!$D$84:$D$87) -> 67600 | K51: =SUM('Premissas gerais'!$D$63:$D$75,'Premissas gerais'!$D$81,'Premissas gerais'!$D$84:$D$87) -> 67600 | L51: =SUM('Premissas gerais'!$D$63:$D$75,'Premissas gerais'!$D$81,'Premissas gerais'!$D$84:$D$87) -> 67600 | M51: =SUM('Premissas gerais'!$D$63:$D$75,'Premissas gerais'!$D$81,'Premissas gerais'!$D$84:$D$87) -> 67600 | N51: =SUM('Premissas gerais'!$D$63:$D$75,'Premissas gerais'!$D$81,'Premissas gerais'!$D$84:$D$87) -> 67600 | O51: =SUM('Premissas gerais'!E63:E75,'Premissas gerais'!E83:E87) -> 99000
C52: Gestão de Trafego e Redes Sociais | D52: ='Premissas gerais'!$B$89+'Premissas gerais'!$B$80 -> 4000 | E52: ='Premissas gerais'!$B$89+'Premissas gerais'!$B$80 -> 4000 | F52: ='Premissas gerais'!$B$89+'Premissas gerais'!$B$80 -> 4000 | G52: ='Premissas gerais'!$B$89+'Premissas gerais'!$B$80 -> 4000 | H52: ='Premissas gerais'!$B$89+'Premissas gerais'!$B$80 -> 4000 | I52: ='Premissas gerais'!$B$89+'Premissas gerais'!$B$80 -> 4000 | J52: ='Premissas gerais'!$B$89+'Premissas gerais'!$B$80 -> 4000 | K52: ='Premissas gerais'!$B$89+'Premissas gerais'!$B$80 -> 4000 | ... O52: ='Premissas gerais'!$B$89+'Premissas gerais'!$B$80 -> 4000
C53: Investimento em Mídia | D53: =2000 -> 2000 | E53: =2000 -> 2000 | F53: =2000 -> 2000 | G53: =2000 -> 2000 | H53: =2000 -> 2000 | I53: =2000 -> 2000 | J53: =2000 -> 2000 | K53: =2000 -> 2000 | ... O53: =2000 -> 2000
C54: Custos Variáveis | D54: =SUM(D55:D62) -> 16674.07 | E54: =SUM(E55:E63) -> 22627.019 | F54: =SUM(F55:F63) -> 25165.535 | G54: =SUM(G55:G63) -> 28190.329 | H54: =SUM(H55:H63) -> 30343.576 | I54: =SUM(I55:I63) -> 34008.179 | J54: =SUM(J55:J63) -> 37279.613 | K54: =SUM(K55:K63) -> 40141.32 | L54: =SUM(L55:L63) -> 43121.299 | ... O54: =SUM(O55:O63) -> 46480.013
C55: Alimentação, Transporte e Reembolsos | D55: =20%*D31 -> 696 | E55: =20%*E31 -> 835.2 | F55: =20%*F31 -> 1113.6 | G55: =20%*G31 -> 1224.96 | H55: =20%*H31 -> 1336.32 | I55: =20%*I31 -> 1447.68 | J55: =20%*J31 -> 1559.04 | K55: =20%*K31 -> 1670.4 | ... O55: =20%*O31 -> 1670.4
C56: Imersão
C57: Reserva Membros | D57: =(D14+D18)*0.5% -> 103.05033 | E57: =(E14+E18)*0.5% -> 239.65033 | F57: =(F14+F18)*0.5% -> 421.78367 | G57: =(G14+G18)*0.5% -> 639.73033 | H57: =(H14+H18)*0.5% -> 774.44 | I57: =(I14+I18)*0.5% -> 916.21333 | J57: =(J14+J18)*0.5% -> 1033.8667 | K57: =(K14+K18)*0.5% -> 1161.12 | ... O57: =(O14+O18)*0.5% -> 1438.3333
C58: Reserva Eventos | D58: =(D14+D18)*1.5% -> 309.151 | E58: =(E14+E18)*1.5% -> 718.951 | F58: =(F14+F18)*1.5% -> 1265.351 | G58: =(G14+G18)*1.5% -> 1919.191 | H58: =(H14+H18)*1.5% -> 2323.32 | I58: =(I14+I18)*1.5% -> 2748.64 | J58: =(J14+J18)*1.5% -> 3101.6 | K58: =(K14+K18)*1.5% -> 3483.36 | ... O58: =(O14+O18)*1.5% -> 4315
C59: Reserva para parceiros | D59: =(D14+D18)*3% -> 618.302 | E59: =(E14+E18)*3% -> 1437.902 | F59: =(F14+F18)*3% -> 2530.702 | G59: =(G14+G18)*3% -> 3838.382 | H59: =(H14+H18)*3% -> 4646.64 | I59: =(I14+I18)*3% -> 5497.28 | J59: =(J14+J18)*3% -> 6203.2 | K59: =(K14+K18)*3% -> 6966.72 | ... O59: =(O14+O18)*3% -> 8630
C60: Reserva de Caixa | D60: =D34*5% -> 6015.058 | E60: =E34*5% -> 5959.3238 | F60: =F34*5% -> 6262.1229 | G60: =G34*5% -> 6865.2375 | H60: =H34*5% -> 7426 | I60: =I34*5% -> 9167.3067 | J60: =J34*5% -> 10796.373 | K60: =K34*5% -> 11996 | ... O60: =O34*5% -> 14968.133
C61: Cartão de Crédito | D61: ='Premissas gerais'!$B$92-D53 -> 7500 | E61: ='Premissas gerais'!$B$92-E53 -> 7500 | F61: ='Premissas gerais'!$B$92-F53 -> 7500 | G61: ='Premissas gerais'!$B$92-G53 -> 7500 | H61: ='Premissas gerais'!$B$92-H53 -> 7500 | I61: ='Premissas gerais'!$B$92-I53 -> 7500 | J61: ='Premissas gerais'!$B$92-J53 -> 7500 | K61: ='Premissas gerais'!$B$92-K53 -> 7500 | ... O61: ='Premissas gerais'!$B$92-O53 -> 7500
C62: Reforma da Sala | D62: =D5*1% -> 1432.509 | E62: =E5*1% -> 1435.9921 | F62: =F5*1% -> 1571.9752 | G62: =G5*1% -> 1702.8282 | H62: =H5*1% -> 1836.856 | I62: =I5*1% -> 2231.0587 | J62: =J5*1% -> 2585.5333 | K62: =K5*1% -> 2863.72 | ... O62: =O5*1% -> 3458.1467
C63: Extras | E63: ='Premissas gerais'!$C$76 -> 4500 | F63: ='Premissas gerais'!$C$76 -> 4500 | G63: ='Premissas gerais'!$C$76 -> 4500 | H63: ='Premissas gerais'!$C$76 -> 4500 | I63: ='Premissas gerais'!$C$76 -> 4500 | J63: ='Premissas gerais'!$C$76 -> 4500 | K63: ='Premissas gerais'!$C$76 -> 4500 | L63: ='Premissas gerais'!$C$76 -> 4500 | ... O63: ='Premissas gerais'!$C$76 -> 4500
C65: Ebtida | D65: =D67-SUM(D68:D69) -> 32946.09 | E65: =E67-SUM(E68:E69) -> 27238.457
C67: Faturamento Total | D67: =D5 -> 143250.9 | E67: =E5 -> 143599.21
C68: Custos Fixos | D68: =D45 -> 87355.07 | E68: =E45 -> 91948.019
C69: Custo de Operação | D69: =SUM(D27) -> 22949.737 | E69: =SUM(E27) -> 24412.73
C70: Lucro Líquido | D70: =D5-SUM(D27,D37,D45) -> 3981.21 | E70: =E5-SUM(E27,E37,E45) -> 1245.2054 | F70: =F5-SUM(F27,F37,F45) -> 4352.6263 | G70: =G5-SUM(G27,G37,G45) -> 11168.045 | H70: =H5-SUM(H27,H37,H45) -> 18043.893 | I70: =I5-SUM(I27,I37,I45) -> 46934.819 | J70: =J5-SUM(J27,J37,J45) -> 56285.929 | K70: =K5-SUM(K27,K37,K45) -> 69182.505 | ... O70: =O5-SUM(O27,O37,O45) -> 72830.145
D76: =SUM(D5:E5)- SUM(D45:E45,D27:E27) -> 60184.547
D77: =SUM(D5:E5)-SUM(D27:E27) -> 239487.64
C78: Margem Bruta | D78: =D77/SUM(D5:E5) -> 0.83488775
C79: Margem Ebitda | D79: =D76/SUM(D5:E5) -> 0.20981184
C80: Lucro Líquido | D80: =SUM(D70:E70) -> 5226.4154
C81: Margem Líquida | D81: =D80/SUM(D5:E5) -> 0.018220023

Sheet Premissas gerais
A1: Funil de Vendas | B1: Numero | C1: /Dias | D1: Indicadores | E1: Taxa | F1: Custo Unitário | N1: Curvas Base / Meses | O1: 1 | P1: 2 | Q1: 3 | R1: 4 | S1: 5 | T1: 6 | U1: 7 | V1: 8 | W1: 9 | X1: 10 | Y1: 11 | Z1: 12 | AA1: Total
A2: Contato | B2: 1200 | C2: =B2/($B$8*30) -> 3.3333333 | F2: =$B$11/B2 -> 640.3375 | L2: Histórico 2025 | M2: Qtd. Vendedores | N2: =AVERAGE(O2:Z2) -> 70166.667 | O2: 18000 | P2: 38000 | Q2: 11000 | R2: 76000 | S2: 64000 | T2: 77000 | U2: 70000 | V2: 105000 | W2: 82000 | X2: 112000 | Y2: 99000 | Z2: 90000 | AA2: =SUM(O2:Z2) -> 842000
A3: Lead | B3: 587 | C3: =B3/($B$8*30) -> 1.6305556 | D3: Lead/Contato | E3: =B3/B2 -> 0.48916667 | F3: =$B$11/B3 -> 1309.0375 | K3: Faturamento Anual | L3: Ref. 2º Sem 2025 | M3: - | N3: =AVERAGE(U2:Z2)*0.9 -> 83700 | O3: =O2/$N$2 -> 0.25653207 | P3: =P2/$N$2 -> 0.5415677 | Q3: =Q2/$N$2 -> 0.1567696 | R3: =R2/$N$2 -> 1.0831354 | S3: =S2/$N$2 -> 0.91211401 | T3: =T2/$N$2 -> 1.0973872 | U3: =U2/$N$2 -> 0.9976247 | V3: =V2/$N$2 -> 1.4964371 | ... Z3: =Z2/$N$2 -> 1.2826603 | AB3: XPEG
A4: Visita | B4: 301 | C4: =B4/($B$8*30) -> 0.83611111 | D4: Visita/Lead | E4: =B4/B3 -> 0.51277683 | F4: =$B$11/B4 -> 2552.8405 | K4: =N4*12 -> 1004400 | L4: Vendedor | M4: 1 | N4: =AVERAGE(O4:Z4) -> 83700 | O4: =O$3*$N$3*$M4 -> 21471.734 | P4: =P$3*$N$3*$M4 -> 45329.216 | Q4: =Q$3*$N$3*$M4 -> 13121.615 | R4: =R$3*$N$3*$M4 -> 90658.432 | S4: =S$3*$N$3*$M4 -> 76343.943 | T4: =T$3*$N$3*$M4 -> 91851.306 | U4: =U$3*$N$3*$M4 -> 83501.188 | V4: =V$3*$N$3*$M4 -> 125251.78 | ... Z4: =Z$3*$N$3*$M4 -> 107358.67 | AA4: =SUM(O4:Z4) -> 1004400
A5: Apresentações/Proposts | B5: 290 | C5: =B5/($B$8*30) -> 0.80555556 | D5: Apresentação/Visita | E5: =B5/B4 -> 0.96345515 | F5: =$B$11/B5 -> 2649.6724 | K5: =N5*12 -> 2008800 | L5: Vendedor | M5: 2 | N5: =M5*N3 -> 167400 | O5: =O$3*$N$3*$M5 -> 42943.468 | P5: =P$3*$N$3*$M5 -> 90658.432 | Q5: =Q$3*$N$3*$M5 -> 26243.23 | R5: =R$3*$N$3*$M5 -> 181316.86 | S5: =S$3*$N$3*$M5 -> 152687.89 | T5: =T$3*$N$3*$M5 -> 183702.61 | U5: =U$3*$N$3*$M5 -> 167002.38 | V5: =V$3*$N$3*$M5 -> 250503.56 | ... Z5: =Z$3*$N$3*$M5 -> 214717.34 | AA5: =SUM(O5:Z5) -> 2008800
A6: Fechamento | B6: =103-6 -> 97 | C6: =B6/($B$8*30) -> 0.26944444 | D6: Fechamento/Apresentação | E6: =B6/B5 -> 0.33448276 | F6: =$B$11/B6 -> 7921.701 | K6: =N6*12 -> 2511000 | L6: Vendedor | M6: 2.5 | N6: =M6*N4 -> 209250 | O6: =O$3*$N$3*$M6 -> 53679.335 | P6: =P$3*$N$3*$M6 -> 113323.04 | Q6: =Q$3*$N$3*$M6 -> 32804.038 | R6: =R$3*$N$3*$M6 -> 226646.08 | S6: =S$3*$N$3*$M6 -> 190859.86 | T6: =T$3*$N$3*$M6 -> 229628.27 | U6: =U$3*$N$3*$M6 -> 208752.97 | V6: =V$3*$N$3*$M6 -> 313129.45 | ... Z6: =Z$3*$N$3*$M6 -> 268396.67 | AA6: =SUM(O6:Z6) -> 2511000
A7: Pós-venda | B7: 21 | C7: =B7/($B$8*30) -> 0.058333333 | D7: Pós-venda/Fechamento | E7: =B7/B6 -> 0.21649485 | F7: =$B$11/B7 -> 36590.714 | K7: =N7*12 -> 3013200 | L7: Vendedor | M7: 3 | N7: =M7*N3 -> 251100 | O7: =O$3*$N$3*$M7 -> 64415.202 | P7: =P$3*$N$3*$M7 -> 135987.65 | Q7: =Q$3*$N$3*$M7 -> 39364.846 | R7: =R$3*$N$3*$M7 -> 271975.3 | S7: =S$3*$N$3*$M7 -> 229031.83 | T7: =T$3*$N$3*$M7 -> 275553.92 | U7: =U$3*$N$3*$M7 -> 250503.56 | V7: =V$3*$N$3*$M7 -> 375755.34 | ... Z7: =Z$3*$N$3*$M7 -> 322076.01 | AA7: =SUM(O7:Z7) -> 3013200
A8: Período de Análise (meses) | B8: 12 | F8: =$B$11/B8 -> 64033.75 | K8: =N8*12 -> 4017600 | L8: Vendedor | M8: 4 | N8: =M8*N3 -> 334800 | O8: =O$3*$N$3*$M8 -> 85886.936 | P8: =P$3*$N$3*$M8 -> 181316.86 | Q8: =Q$3*$N$3*$M8 -> 52486.461 | R8: =R$3*$N$3*$M8 -> 362633.73 | S8: =S$3*$N$3*$M8 -> 305375.77 | T8: =T$3*$N$3*$M8 -> 367405.23 | U8: =U$3*$N$3*$M8 -> 334004.75 | V8: =V$3*$N$3*$M8 -> 501007.13 | ... Z8: =Z$3*$N$3*$M8 -> 429434.68 | AA8: =SUM(O8:Z8) -> 4017600
A9: Fechamento Mensal | B9: =B6/B8 -> 8.0833333 | F9: =$B$11/B9 -> 95060.412
A10: Total Orçado | B10: =2533162.95-130000 -> 2403163 | C10: =B10/($B$8*(365/12)) -> 6584.0081 | F10: =E11*B10 -> 768405
A11: Total Fechado | B11: 768405 | C11: =B11/($B$8*365/12) -> 2105.2192 | D11: Fechado/Orçado (R$) | E11: =B11/B10 -> 0.31974736 | L11: =N7/8000 -> 31.3875
A12: Qtd Total de Orçamentos | B12: 301 | C12: =B12/($B$8*365/12) -> 0.82465753 | L12: =L11*3 -> 94.1625
A13: Qtd Total de Fechamentos | B13: =B6 -> 97 | C13: =B13/($B$8*365/12) -> 0.26575342 | D13: Fechado/Orçado (Qtd) | E13: =B13/B12 -> 0.32225914 | L13: =L12*2 -> 188.325 | N13: Histórico de Orçamentos | O13: 86000 | P13: 103000 | Q13: 82000 | R13: 200000 | S13: 153000 | T13: 143000 | U13: 268000 | V13: 335000 | W13: 295000 | X13: 232000 | Y13: 203000 | Z13: 200000 | AA13: =SUM(O13:Z13) -> 2300000
A15: Indicadores por Vendedor por Mês | C15: Indicadores Originais 2025 | D15: Taxa (%) | E15: Valor Simulado | G15: Projeção Simplificada | H15: Mês | I15: Ano | L15: 5000 | N15: antes | O15: 18000 | P15: 38000 | Q15: 11000 | R15: 76000 | S15: 64000 | T15: 77000 | U15: 70000 | V15: 105000 | W15: 82000 | X15: 112000 | Y15: 99000 | Z15: 90000 | AA15: =SUM(O15:Z15) -> 842000
A16: Qtd. de Vendedores | B16: 2 | C16: 1 | D16: 1 | E16: Qtd de Vendedores | F16: =D16*B16 -> 2 | G16: Qtd. Vendedores | H16: 2 | L16: =L13/L15 -> 0.037665 | N16: dinheiro em caixa | O16: 20000 | P16: 23000 | Q16: 10000 | R16: 20000 | S16: 38000 | T16: 34000 | U16: 53000 | V16: 71000 | W16: 66000 | X16: 83000 | Y16: 83000 | Z16: 75000
A17: Qtd. Contatos | B17: =B2/($B$8*$B$16) -> 50 | C17: 1 | D17: 3.2 | E17: Qtd de Contatos | F17: =D17*B17 -> 160 | G17: Contatos | H17: =F17*$H$16 -> 320 | I17: =H17*12 -> 3840
A18: Qtd. Lead | B18: =B3/($B$8*$B$16) -> 24.458333 | C18: 0.48916667 | D18: =E3 -> 0.48916667 | E18: Lead/Contato | F18: =F17*D18 -> 78.266667 | G18: Lead | H18: =F18*$H$16 -> 156.53333 | I18: =H18*12 -> 1878.4
A19: Qtd. Visita | B19: =B4/($B$8*$B$16) -> 12.541667 | C19: 0.51277683 | D19: =E4 -> 0.51277683 | E19: Visita/Lead | F19: =F18*D19 -> 40.133333 | G19: Visita | H19: =F19*$H$16 -> 80.266667 | I19: =H19*12 -> 963.2
A20: Qtd. Apresentações | B20: =B5/($B$8*$B$16) -> 12.083333 | C20: 0.96345515 | D20: =E5 -> 0.96345515 | E20: Apresentação/Visita | F20: =F19*D20 -> 38.666667 | G20: Apresentações | H20: =F20*$H$16 -> 77.333333 | I20: =H20*12 -> 928
A21: Qtd. Fechamento | B21: =B6/($B$8*$B$16) -> 4.0416667 | C21: 0.33448276 | D21: =E6 -> 0.33448276 | E21: Fechamento/Apresentação | F21: =F20*D21 -> 12.933333 | G21: Fechamento | H21: =F21*$H$16 -> 25.866667 | I21: =H21*12 -> 310.4
A22: Qtd. Pós-venda | B22: =B7/($B$8*$B$16) -> 0.875 | C22: 0.21649485 | D22: =E7 -> 0.21649485 | E22: Pós-venda/Fechamento | F22: =F21*D22 -> 2.8 | G22: Pós-venda | H22: =F22*$H$16 -> 5.6 | I22: =H22*12 -> 67.2
A23: Total Orçado | B23: =B10/($B$8*$B$16) -> 100131.79 | C23: 1 | D23: =B12/$B$4 -> 1 | E23: Orçamentos/Visita | F23: =D23*B25 -> 12.541667 | G23: Faturamento | H23: =F27*F26*H16 -> 196035.69 | I23: =H23*12 -> 2352428.3
A24: Total Fechado | B24: =B11/($B$8*$B$16) -> 32016.875 | C24: 0.32225914 | D24: =B13/$B$4 -> 0.32225914 | E24: Fechamento/Orçamento | F24: =D24*F23 -> 4.0416667
A25: Qtd. Orçamentos | B25: =B12/($B$8*$B$16) -> 12.541667 | C25: 1 | D25: 1 | E25: Orçamentos/mês | F25: =F20 -> 38.666667
A26: Qtd. Fechamentos | B26: =B13/($B$8*$B$16) -> 4.0416667 | C26: =E13 -> 0.32225914 | D26: 0.32 | E26: Fechamentos/mês | F26: =D26*F25 -> 12.373333
A27: Ticket Médio | B27: =B24/B26 -> 7921.701 | C27: 1 | D27: 1 | E27: Novo Ticket Médio | F27: =D27*B27 -> 7921.701
E28: Faturamento Mensal/Vendedor | F28: =F27*F26 -> 98017.847
A30: Margem Lucro Operacional | B30: R$ | C30: %
A31: Ticket Médio | B31: =F27 -> 7921.701 | C31: 1
A32: Imposto | B32: =C32*B31 -> 1267.4722 | C32: 0.16
A33: Custo Operacional | B33: =B31*C33 -> 3168.6804 | C33: 0.4
A34: Custo de Vendas | B34: =C34*B31 -> 792.1701 | C34: 0.1
A35: Orçamento Mkt + CS + Relac. | B35: =C35*B31 -> 396.08505 | C35: 0.05
A36: Margem Bruta | B36: =B31-B32-B33-B34-B35 -> 2297.2933 | C36: =B36/B31 -> 0.29
A37: Prática 1/4 cai no mês | B37: =B36/4 -> 574.32332
A40: Custo Fixo | B40: =SUM(B41:B48) -> 15000 | C40: Total
A41: Aluguel + Dívida | B41: 10000 | E41: =10*30*12 -> 3600
A42: Outros custos | B42: 5000 | E42: =11*0.5*1500 -> 8250
A43: - | B43: =B41*C43 -> 0 | E43: 3000
A44: - | B44: =B42*C44 -> 0
B51: Hoje | D51: Projetado 2026 | H51: Ticket
A52: Margens dos Projetos | B52: % | C52: Qtd. Mensal | D52: Qtd. | E52: Mão de obra | F52: Custo Hoje | G52: Custo futuro
A53: Disponibilidade | B53: 0.68 | C53: =3*4.28 -> 12.84 | D53: 22 | F53: =H53*(1-B53) -> 2560 | H53: 8000
A54: Projeto* CDM | B54: 0.65 | C54: 4 | D54: 8 | F54: =H54*(1-B54) -> 1750 | H54: 5000
A55: Laudo + G. Risco | B55: 0.62 | C55: 4 | D55: 10 | F55: =H55*(1-B55) -> 2660 | H55: 7000
B57: 1500
C58: =30*10000*10% -> 30000
A62: Custo bruto folha | B62: atual | C62: Fev | D62: Julho | E62: Dez
A63: Jonildo | B63: 6100 | C63: 7000 | D63: 8500 | E63: 10000
A64: Gabriel | B64: 3000 | C64: 6000 | D64: =C64 -> 6000 | E64: 6000
A65: Igor | B65: 1700 | C65: 5000 | D65: =C65 -> 5000 | E65: 5000 | N65: 500k
A66: Fernando | B66: 4000 | C66: 4000 | D66: 6000 | E66: 14000
A67: Belo | B67: 3500 | C67: =B67 -> 3500 | D67: 5000 | E67: 10000
A68: Decézaris | B68: 4500 | C68: =B68 -> 4500 | D68: 6500 | E68: 10000
A69: Adryan | B69: 1500 | C69: 3200 | D69: 5500 | E69: 7500
A70: Macgyver | B70: 5100 | C70: =B70 -> 5100 | D70: =C70 -> 5100 | E70: 6000
A71: Diogo | B71: 2500 | C71: 2500 | D71: 3500 | E71: 4500
A72: Audrey | B72: 2500 | C72: 2500 | D72: 3500 | E72: 4500
A73: Est. Igor | B73: 1000 | C73: 1500 | D73: 1500 | E73: 2000
A74: Est. P. Araújo | B74: 1000 | C74: 1300 | D74: 1500 | E74: 2000
A75: Est. Tawanny | B75: 1000 | C75: 1000 | D75: 1000 | E75: 1500
A76: Leon | B76: 900 | C76: 4500 | D76: 4500 | E76: 4500
A77: Jurídico | B77: 1100 | C77: =B77 -> 1100 | D77: =C77 -> 1100 | E77: =D77 -> 1100
A78: Contabilidade | B78: 400 | C78: 1600 | D78: =C78 -> 1600 | E78: =D78 -> 1600
A79: Tráfego Pago | B79: 2000 | C79: =B79 -> 2000 | D79: =C79 -> 2000 | E79: =D79 -> 2000
A80: Marketing | B80: 2000 | C80: =B80 -> 2000 | D80: =C80 -> 2000 | E80: =D80 -> 2000
A81: RH | B81: 0 | C81: 1000 | D81: =C81 -> 1000 | E81: =D81 -> 1000
A82: Est. P. Barroso | B82: 500 | C82: 0
A83: Novo Vendedor | B83: 0 | E83: 5000
A84: Est. Cleber | B84: 1000 | C84: 2000 | D84: 3000 | E84: 5000
A85: João | B85: 1000 | C85: 2000 | D85: 2000 | E85: 2000
A86: Kalebe | B86: 1000 | C86: 1500 | D86: 2000 | E86: 3000
A87: Everaldo | B87: 1500 | C87: 1000 | D87: 1000 | E87: 1000
A88: Filipe | B88: 2500
A89: Anúncios | B89: 2000 | C89: =B89 -> 2000 | D89: =C89 -> 2000 | E89: =D89 -> 2000
A90: Sala | B90: 7000 | C90: =B90 -> 7000 | D90: =C90 -> 7000 | E90: =D90 -> 7000
A91: Reembolsos e despesas | B91: 3000 | C91: =B91 -> 3000 | D91: =C91 -> 3000 | E91: =D91 -> 3000
A92: Cartão de Crédito | B92: =9000+500 -> 9500 | C92: =B92 -> 9500 | D92: =C92 -> 9500 | E92: =D92 -> 9500
A93: Empréstimo | B93: 6400 | C93: =B93 -> 6400 | D93: =C93 -> 6400 | E93: =D93 -> 6400
A94: Administrativo | B94: 2721 | C94: =B94 -> 2721 | D94: =C94 -> 2721 | E94: =D94 -> 2721
A95: Outros custos de material para projetos | B95: 4000 | C95: =B95 -> 4000 | D95: =C95 -> 4000 | E95: =D95 -> 4000
A96: Francisco
A97: Marcelo
A99: Total | B99: =SUM(B63:B98) -> 85921 | C99: =SUM(C63:C98) -> 100421 | D99: =SUM(D63:D98) -> 113421 | E99: =SUM(E63:E98) -> 145821
C100: =C99-B99 -> 14500 | D100: =D99-B99 -> 27500 | E100: =E99-B99 -> 59900 | G100: =1100+400 -> 1500
C101: =C100*2 -> 29000 | D101: =D100*2 -> 55000 | E101: =E100*2 -> 119800 | G101: =1100+1621 -> 2721
B104: Total | C104: Qtd
A105: Faturamento Obras | B105: 110000 | C105: 6
A106: Qtd de Consultorias Mês
N112: =(B114+C114+D114+E114+F114+G114+H114+I114+J114+K114+L114+M114) -> 1113345.2 | O112: =(C114+D114+E114+F114+G114+H114+I114+J114+K114+L114+M114+N114) -> 1194435.7 | P112: =(D114+E114+F114+G114+H114+I114+J114+K114+L114+M114+N114+O114) -> 1268592 | Q112: =(E114+F114+G114+H114+I114+J114+K114+L114+M114+N114+O114+P114) -> 1364979.1 | R112: =(F114+G114+H114+I114+J114+K114+L114+M114+N114+O114+P114+Q114) -> 1469170.7 | S112: =(G114+H114+I114+J114+K114+L114+M114+N114+O114+P114+Q114+R114) -> 1586700.2 | T112: =(H114+I114+J114+K114+L114+M114+N114+O114+P114+Q114+R114+S114) -> 1729335.8 | U112: =(I114+J114+K114+L114+M114+N114+O114+P114+Q114+R114+S114+T114) -> 1878903.9 | ... Y112: =(M114+N114+O114+P114+Q114+R114+S114+T114+U114+V114+W114+X114) -> 2722531.8
A113: Histórico de Faturamento | B113: 1 | C113: 2 | D113: 3 | E113: 4 | F113: 5 | G113: 6 | H113: 7 | I113: 8 | J113: 9 | K113: 10 | L113: 11 | M113: 12 | N113: 1 | O113: 2 | P113: 3 | Q113: 4 | R113: 5 | S113: 6 | T113: 7 | U113: 8 | V113: 9 | W113: 10 | X113: 11 | Y113: 12
A114: =SUM(B114:M114) -> 1113345.2 | B114: 62160.33 | C114: 69442.98 | D114: 60810.41 | E114: 66091.21 | F114: 66156.1 | G114: 80470.22 | H114: 108985.3 | I114: 103723.42 | J114: 100903.61 | K114: 125613.86 | L114: 110827.73 | M114: 158160 | N114: ='Resumão Geral'!D5 -> 143250.9 | O114: ='Resumão Geral'!E5 -> 143599.21 | P114: ='Resumão Geral'!F5 -> 157197.52 | Q114: ='Resumão Geral'!G5 -> 170282.82 | R114: ='Resumão Geral'!H5 -> 183685.6 | S114: ='Resumão Geral'!I5 -> 223105.87 | T114: ='Resumão Geral'!J5 -> 258553.33 | U114: ='Resumão Geral'!K5 -> 286372 | ... Y114: ='Resumão Geral'!O5 -> 345814.67
M115: Faixa 3 | N115: =(((B114+C114+D114+E114+F114+G114+H114+I114+J114+K114+L114+M114)*$D$116)-$E$116)/(B114+C114+D114+E114+F114+G114+H114+I114+J114+K114+L114+M114) -> 0.12798836 | O115: =(((C114+D114+E114+F114+G114+H114+I114+J114+K114+L114+M114+N114)*$D$116)-$E$116)/(C114+D114+E114+F114+G114+H114+I114+J114+K114+L114+M114+N114) -> 0.13016164 | P115: =(((D114+E114+F114+G114+H114+I114+J114+K114+L114+M114+N114+O114)*$D$116)-$E$116)/(D114+E114+F114+G114+H114+I114+J114+K114+L114+M114+N114+O114) -> 0.13190586 | Q115: =(((E114+F114+G114+H114+I114+J114+K114+L114+M114+N114+O114+P114)*$D$116)-$E$116)/(E114+F114+G114+H114+I114+J114+K114+L114+M114+N114+O114+P114) -> 0.13388971 | R115: =(((F114+G114+H114+I114+J114+K114+L114+M114+N114+O114+P114+Q114)*$D$116)-$E$116)/(F114+G114+H114+I114+J114+K114+L114+M114+N114+O114+P114+Q114) -> 0.13574142 | S115: =(((G114+H114+I114+J114+K114+L114+M114+N114+O114+P114+Q114+R114)*$D$116)-$E$116)/(G114+H114+I114+J114+K114+L114+M114+N114+O114+P114+Q114+R114) -> 0.13753829 | T115: =(((H114+I114+J114+K114+L114+M114+N114+O114+P114+Q114+R114+S114)*$D$116)-$E$116)/(H114+I114+J114+K114+L114+M114+N114+O114+P114+Q114+R114+S114) -> 0.13939093 | U115: =(((I114+J114+K114+L114+M114+N114+O114+P114+Q114+R114+S114+T114)*$D$116)-$E$116)/(I114+J114+K114+L114+M114+N114+O114+P114+Q114+R114+S114+T114) -> 0.14103149 | ... Y115: =(((M114+N114+O114+P114+Q114+R114+S114+T114+U114+V114+W114+X114)*$D$116)-$E$116)/(M114+N114+O114+P114+Q114+R114+S114+T114+U114+V114+W114+X114) -> 0.14690924
A116: se total faturado 12 meses > R$1.800.000,00 | D116: 0.16 | E116: 35640 | M116: Faixa 4 | N116: =(((B114+C114+D114+E114+F114+G114+H114+I114+J114+K114+L114+M114)*$D$117)-$E$117)/(B114+C114+D114+E114+F114+G114+H114+I114+J114+K114+L114+M114) -> 0.0971509 | O116: =(((C114+D114+E114+F114+G114+H114+I114+J114+K114+L114+M114+N114)*$D$117)-$E$117)/(C114+D114+E114+F114+G114+H114+I114+J114+K114+L114+M114+N114) -> 0.10481226 | P116: =(((D114+E114+F114+G114+H114+I114+J114+K114+L114+M114+N114+O114)*$D$117)-$E$117)/(D114+E114+F114+G114+H114+I114+J114+K114+L114+M114+N114+O114) -> 0.11096106 | Q116: =(((E114+F114+G114+H114+I114+J114+K114+L114+M114+N114+O114+P114)*$D$117)-$E$117)/(E114+F114+G114+H114+I114+J114+K114+L114+M114+N114+O114+P114) -> 0.11795463 | R116: =(((F114+G114+H114+I114+J114+K114+L114+M114+N114+O114+P114+Q114)*$D$117)-$E$117)/(F114+G114+H114+I114+J114+K114+L114+M114+N114+O114+P114+Q114) -> 0.12448237 | S116: =(((G114+H114+I114+J114+K114+L114+M114+N114+O114+P114+Q114+R114)*$D$117)-$E$117)/(G114+H114+I114+J114+K114+L114+M114+N114+O114+P114+Q114+R114) -> 0.1308168 | T116: =(((H114+I114+J114+K114+L114+M114+N114+O114+P114+Q114+R114+S114)*$D$117)-$E$117)/(H114+I114+J114+K114+L114+M114+N114+O114+P114+Q114+R114+S114) -> 0.13734783 | U116: =(((I114+J114+K114+L114+M114+N114+O114+P114+Q114+R114+S114+T114)*$D$117)-$E$117)/(I114+J114+K114+L114+M114+N114+O114+P114+Q114+R114+S114+T114) -> 0.14313122 | ... Y116: =(((M114+N114+O114+P114+Q114+R114+S114+T114+U114+V114+W114+X114)*$D$117)-$E$117)/(M114+N114+O114+P114+Q114+R114+S114+T114+U114+V114+W114+X114) -> 0.16385178
D117: 0.21 | E117: 125640 | N117: =IF(N112>1800000,N116,N115) -> 0.12798836 | O117: =IF(O112>1800000,O116,O115) -> 0.13016164 | P117: =IF(P112>1800000,P116,P115) -> 0.13190586 | Q117: =IF(Q112>1800000,Q116,Q115) -> 0.13388971 | R117: =IF(R112>1800000,R116,R115) -> 0.13574142 | S117: =IF(S112>1800000,S116,S115) -> 0.13753829 | T117: =IF(T112>1800000,T116,T115) -> 0.13939093 | U117: =IF(U112>1800000,U116,U115) -> 0.14313122 | ... Y117: =IF(Y112>1800000,Y116,Y115) -> 0.16385178
A121: Custo bruto obra
A122: Material | B122: 0.4
A123: Imposto
A124: Felipe | B124: 2500
A125: Administrativo | B125: 500
...

Sheet Projeção Biel Ajustada
A1: Faturamento Consultoria
A2: Mês | B2: Total | C2: Média | D2: Referência | E2: 1 | F2: 2 | G2: 3 | H2: 4 | I2: 5 | J2: 6 | K2: 7 | L2: 8 | M2: 9 | N2: 10 | O2: 11 | P2: 12
A3: Curva Faturamento R$ | B3: =SUM(E3:P3) -> 2008800 | C3: =AVERAGE(E3:P3) -> 167400 | E3: ='Premissas gerais'!O5 -> 42943.468 | F3: ='Premissas gerais'!P5 -> 90658.432 | G3: ='Premissas gerais'!Q5 -> 26243.23 | H3: ='Premissas gerais'!R5 -> 181316.86 | I3: ='Premissas gerais'!S5 -> 152687.89 | J3: ='Premissas gerais'!T5 -> 183702.61 | K3: ='Premissas gerais'!U5 -> 167002.38 | L3: ='Premissas gerais'!V5 -> 250503.56 | ... P3: ='Premissas gerais'!Z5 -> 214717.34
A4: Curva Faturamento % | B4: 1 | C4: =AVERAGE(E4:P4) -> 1 | E4: =E3/$C$3 -> 0.25653207 | F4: =F3/$C$3 -> 0.5415677 | G4: =G3/$C$3 -> 0.1567696 | H4: =H3/$C$3 -> 1.0831354 | I4: =I3/$C$3 -> 0.91211401 | J4: =J3/$C$3 -> 1.0973872 | K4: =K3/$C$3 -> 0.9976247 | L4: =L3/$C$3 -> 1.4964371 | ... P4: =P3/$C$3 -> 1.2826603 | V4: c1 | W4: c2 | X4: c3 | Y4: c4 | AA4: c1 | AB4: c2 | AC4: c3 | AD4: c4
A5: Qtd Vendedores | B5: =C5 -> 2 | C5: =AVERAGE(E5:P5) -> 2 | D5: 2 | E5: =D5 -> 2 | F5: =E5 -> 2 | G5: =F5 -> 2 | H5: =G5 -> 2 | I5: =H5 -> 2 | J5: =I5 -> 2 | K5: 2 | L5: =K5 -> 2 | M5: =L5 -> 2 | N5: =M5 -> 2 | O5: =N5 -> 2 | P5: =O5 -> 2 | U5: Ticket médio | V5: 10000 | W5: 10000 | X5: 10000 | Y5: 10000 | Z5: Ticket médio | AA5: 10000 | AB5: 10000 | AC5: 10000 | AD5: 10000
A6: Funil de Vendas Atual | B6: 84 | E6: 84 | U6: Comissão % | V6: 0 | W6: 0.05 | X6: 0.1 | Y6: 0.15 | Z6: Comissão % | AA6: 0 | AB6: 0.025 | AC6: 0.05 | AD6: 0.1
A7: Topo de Funil (Indicações/oportunidades) | B7: =SUM(E7:P7) -> 907.5 | E7: =E8*3 -> 37.5 | F7: =F8*3 -> 45 | G7: =G8*3 -> 60 | H7: =H8*3 -> 66 | I7: =I8*3 -> 72 | J7: =J8*3 -> 78 | K7: =K8*3 -> 84 | L7: =L8*3 -> 90 | ... P7: =P8*3 -> 90 | U7: Qtd de Vendas Méd | V7: 3 | W7: 7 | X7: 10 | Y7: 12 | Z7: Qtd de Vendas Méd | AA7: 4 | AB7: 7 | AC7: 12 | AD7: 14
A8: Qtd Visita / Vendedor | B8: =SUM(E8:P8) -> 302.5 | C8: =AVERAGE(E8:P8) -> 25.208333 | D8: 12.5 | E8: =D8 -> 12.5 | F8: 15 | G8: 20 | H8: 22 | I8: 24 | J8: 26 | K8: 28 | L8: 30 | M8: 32 | N8: 33 | O8: 30 | P8: 30 | U8: Faturamento total | V8: =V7*V5 -> 30000 | W8: =W7*W5 -> 70000 | X8: =X7*X5 -> 100000 | Y8: =Y7*Y5 -> 120000 | Z8: Faturamento total | AA8: =AA7*AA5 -> 40000 | AB8: =AB7*AB5 -> 70000 | AC8: =AC7*AC5 -> 120000 | AD8: =AD7*AD5 -> 140000
A9: Total de Propostas | B9: =SUM(E9:P9) -> 605 | C9: =AVERAGE(E9:P9) -> 50.416667 | D9: =E8*E5 -> 25 | E9: =E5*E8 -> 25 | F9: =F5*F8 -> 30 | G9: =G5*G8 -> 40 | H9: =H5*H8 -> 44 | I9: =I5*I8 -> 48 | J9: =J5*J8 -> 52 | K9: =K5*K8 -> 56 | L9: =L5*L8 -> 60 | ... P9: =P5*P8 -> 60 | U9: Fixo | V9: 4000 | W9: =V9 -> 4000 | X9: =W9 -> 4000 | Y9: =X9 -> 4000 | Z9: Fixo | AA9: 5000 | AB9: =AA9 -> 5000 | AC9: =AB9 -> 5000 | AD9: =AC9 -> 5000
A10: Taxa de Conversa Prop/Fech | B10: =SUM(E10:P10) -> 3.84 | C10: =AVERAGE(E10:P10) -> 0.32 | D10: 3.32 | E10: 0.32 | F10: 0.32 | G10: 0.32 | H10: 0.32 | I10: 0.32 | J10: 0.32 | K10: 0.32 | L10: 0.32 | M10: 0.32 | N10: 0.32 | O10: 0.32 | P10: 0.32 | U10: Variável | V10: =V6*V8 -> 0 | W10: =W6*W8 -> 3500 | X10: =X6*X8 -> 10000 | Y10: =Y6*Y8 -> 18000 | Z10: Variável | AA10: =AA6*AA8 -> 0 | AB10: =AB6*AB8 -> 1750 | AC10: =AC6*AC8 -> 6000 | AD10: =AD6*AD8 -> 14000
A11: Total de Fechamentos | B11: =SUM(E11:P11) -> 193.6 | C11: =AVERAGE(D11:P11) -> 15.507692 | D11: =E10*E9 -> 8 | E11: =E10*E9 -> 8 | F11: =F10*F9 -> 9.6 | G11: =G10*G9 -> 12.8 | H11: =H10*H9 -> 14.08 | I11: =I10*I9 -> 15.36 | J11: =J10*J9 -> 16.64 | K11: =K10*K9 -> 17.92 | L11: =L10*L9 -> 19.2 | ... P11: =P10*P9 -> 19.2 | U11: Comissão + Var = R$ | V11: =V9+V8*V6 -> 4000 | W11: =W9+W8*W6 -> 7500 | X11: =X9+X8*X6 -> 14000 | Y11: =Y9+Y8*Y6 -> 22000 | Z11: Comissão + Var = R$ | AA11: =AA9+AA8*AA6 -> 5000 | AB11: =AB9+AB8*AB6 -> 6750 | AC11: =AC9+AC8*AC6 -> 11000 | AD11: =AD9+AD8*AD6 -> 19000
A12: Ticket médio | D12: 7921.7 | E12: =D12 -> 7921.7 | F12: 9000 | G12: 9000 | H12: 10000 | I12: 10000 | J12: 11000 | K12: =J12 -> 11000 | L12: 12000 | M12: =L12 -> 12000 | N12: =M12 -> 12000 | O12: =N12 -> 12000 | P12: =O12 -> 12000 | U12: % Vendas / Faturamento | V12: =V9/V8 -> 0.13333333 | W12: =W9/W8 -> 0.057142857 | X12: =X9/X8 -> 0.04 | Y12: =Y9/Y8 -> 0.033333333 | Z12: % Vendas / Faturamento | AA12: =AA9/AA8 -> 0.125 | AB12: =AB9/AB8 -> 0.071428571 | AC12: =AC9/AC8 -> 0.041666667 | AD12: =AD9/AD8 -> 0.035714286
A13: Faturamento Novas vendas | B13: =SUM(E13:P13) -> 2129933.6 | C13: =AVERAGE(E13:P13) -> 177494.47 | D13: =AVERAGE(E12:P12) -> 10660.142 | E13: =E12*E11 -> 63373.6 | F13: =F12*F11 -> 86400 | G13: =G12*G11 -> 115200 | H13: =H12*H11 -> 140800 | I13: =I12*I11 -> 153600 | J13: =J12*J11 -> 183040 | K13: =K12*K11 -> 197120 | L13: =L12*L11 -> 230400 | ... P13: =P12*P11 -> 230400 | U13: Contribuição R$ | V13: =V8-V11 -> 26000 | W13: =W8-W11 -> 62500 | X13: =X8-X11 -> 86000 | Y13: =Y8-Y11 -> 98000 | Z13: Contribuição R$ | AA13: =AA8-AA11 -> 35000 | AB13: =AB8-AB11 -> 63250 | AC13: =AC8-AC11 -> 109000 | AD13: =AD8-AD11 -> 121000
A14: Parcela 1 | E14: =E13/4 -> 15843.4 | F14: =F13/4 -> 21600 | G14: =G13/4 -> 28800 | H14: =H13/4 -> 35200 | I14: =I13/4 -> 38400 | J14: =J13/4 -> 45760 | K14: =K13/4 -> 49280 | L14: =L13/4 -> 57600 | ... P14: =P13/4 -> 57600 | U14: Entrada Mínima 25% | V14: =25%*V8 -> 7500 | W14: =25%*W8 -> 17500 | X14: =25%*X8 -> 25000 | Y14: =25%*Y8 -> 30000 | Z14: Entrada Mínima 25% | AA14: =25%*AA8 -> 10000 | AB14: =25%*AB8 -> 17500 | AC14: =25%*AC8 -> 30000 | AD14: =25%*AD8 -> 35000
A15: Parcela 2 | F15: =E14 -> 15843.4 | G15: =F14 -> 21600 | H15: =G14 -> 28800 | I15: =H14 -> 35200 | J15: =I14 -> 38400 | K15: =J14 -> 45760 | L15: =K14 -> 49280 | M15: =L14 -> 57600 | ... P15: =O14 -> 57600 | U15: Diferença | V15: =V14-V11 -> 3500 | W15: =W14-W11 -> 10000 | X15: =X14-X11 -> 11000 | Y15: =Y14-Y11 -> 8000 | Z15: Diferença | AA15: =AA14-AA11 -> 5000 | AB15: =AB14-AB11 -> 10750 | AC15: =AC14-AC11 -> 19000 | AD15: =AD14-AD11 -> 16000
A16: Parcela 3 | G16: =F15 -> 15843.4 | H16: =G15 -> 21600 | I16: =H15 -> 28800 | J16: =I15 -> 35200 | K16: =J15 -> 38400 | L16: =K15 -> 45760 | M16: =L15 -> 49280 | N16: =M15 -> 57600 | ... P16: =O15 -> 63360
A17: Parcela 4 | H17: =G16 -> 15843.4 | I17: =H16 -> 21600 | J17: =I16 -> 28800 | K17: =J16 -> 35200 | L17: =K16 -> 38400 | M17: =L16 -> 45760 | N17: =M16 -> 49280 | O17: =N16 -> 57600 | P17: =O16 -> 61440
A18: Total das Parcelas | E18: =SUM(E14:E17) -> 15843.4 | F18: =SUM(F14:F17) -> 37443.4 | G18: =SUM(G14:G17) -> 66243.4 | H18: =SUM(H14:H17) -> 101443.4 | I18: =SUM(I14:I17) -> 124000 | J18: =SUM(J14:J17) -> 148160 | K18: =SUM(K14:K17) -> 168640 | L18: =SUM(L14:L17) -> 191040 | ... P18: =SUM(P14:P17) -> 240000 | AA18: 8 | AB18: 14 | AC18: 24 | AD18: 28
A19: Acumulado de Negócios | D19: 1 | E19: =E11 -> 8 | F19: =F11+E19 -> 17.6 | G19: =G11+F19 -> 30.4 | H19: =H11+G19 -> 44.48 | I19: =I11+H19 -> 59.84 | J19: =J11+I19 -> 76.48 | K19: =K11+J19 -> 94.4 | L19: =L11+K19 -> 113.6 | M19: =M11+L19 -> 134.08 | ... P19: =P11+O19 -> 193.6 | AA19: sobrev | AB19: os import. prim. | AC19: justo correto | AD19: overdelivery
A20: Acumulado de Faturamento | E20: =E13 -> 63373.6 | F20: =F13+E20 -> 149773.6 | G20: =G13+F20 -> 264973.6 | H20: =H13+G20 -> 405773.6 | I20: =I13+H20 -> 559373.6 | J20: =J13+I20 -> 742413.6 | K20: =K13+J20 -> 939533.6 | L20: =L13+K20 -> 1169933.6 | M20: =M13+L20 -> 1415693.6 | ... P20: =P13+O20 -> 2129933.6 | AB20: 10000 | AC20: 19000
A21: Distribuição Faturamento Curva | D21: =AVERAGE(E13:P13) -> 177494.47 | E21: =E4*$D$21 -> 45533.022 | F21: =F4*$D$21 -> 96125.269 | G21: =G4*$D$21 -> 27825.736 | H21: =H4*$D$21 -> 192250.54 | I21: =I4*$D$21 -> 161895.19 | J21: =J4*$D$21 -> 194780.15 | K21: =K4*$D$21 -> 177072.86 | L21: =L4*$D$21 -> 265609.3 | ... P21: =P4*$D$21 -> 227665.11
A22: Comissão (prevista) | D22: 0.05 | E22: =$D$22*E13 -> 3168.68 | F22: =$D$22*F13 -> 4320 | G22: =$D$22*G13 -> 5760 | H22: =$D$22*H13 -> 7040 | I22: =$D$22*I13 -> 7680 | J22: =$D$22*J13 -> 9152 | K22: =$D$22*K13 -> 9856 | L22: =$D$22*L13 -> 11520 | ... P22: =$D$22*P13 -> 11520 | T22: =$D$22*T13 -> 0
A23: Comissão Parcela 1 | D23: =D22 -> 0.05 | E23: =E22/4 -> 792.17 | F23: =F22/4 -> 1080 | G23: =G22/4 -> 1440 | H23: =H22/4 -> 1760 | I23: =I22/4 -> 1920 | J23: =J22/4 -> 2288 | K23: =K22/4 -> 2464 | L23: =L22/4 -> 2880 | ... P23: =P22/4 -> 2880 | T23: =T22/4 -> 0
A24: Comissão Parcela 2 | D24: =D23 -> 0.05 | F24: =E22/4 -> 792.17 | G24: =F22/4 -> 1080 | H24: =G22/4 -> 1440 | I24: =H22/4 -> 1760 | J24: =I22/4 -> 1920 | K24: =J22/4 -> 2288 | L24: =K22/4 -> 2464 | M24: =L22/4 -> 2880 | ... P24: =O22/4 -> 2880 | T24: =S22/4 -> 0
A25: Comissão Parcela 3 | D25: =D24 -> 0.05 | G25: =E22/4 -> 792.17 | H25: =F22/4 -> 1080 | I25: =G22/4 -> 1440 | J25: =H22/4 -> 1760 | K25: =I22/4 -> 1920 | L25: =J22/4 -> 2288 | M25: =K22/4 -> 2464 | N25: =L22/4 -> 2880 | ... P25: =N22/4 -> 3168 | T25: =R22/4 -> 0
A26: Comissão Parcela 4 | D26: =D25 -> 0.05 | H26: =E22/4 -> 792.17 | I26: =F22/4 -> 1080 | J26: =G22/4 -> 1440 | K26: =H22/4 -> 1760 | L26: =I22/4 -> 1920 | M26: =J22/4 -> 2288 | N26: =K22/4 -> 2464 | O26: =L22/4 -> 2880 | P26: =M22/4 -> 3072 | T26: =Q22/4 -> 0
A27: Total de Comissão (P1 + P2 + P3 + P4) | E27: =SUM(E23:E26) -> 792.17 | F27: =SUM(F23:F26) -> 1872.17 | G27: =SUM(G23:G26) -> 3312.17 | H27: =SUM(H23:H26) -> 5072.17 | I27: =SUM(I23:I26) -> 6200 | J27: =SUM(J23:J26) -> 7408 | K27: =SUM(K23:K26) -> 8432 | L27: =SUM(L23:L26) -> 9552 | ... P27: =SUM(P23:P26) -> 12000 | T27: =SUM(T23:T26) -> 0
A28: % Comissão / Faturamento | E28: =E27/E18 -> 0.05 | F28: =F27/F18 -> 0.05 | G28: =G27/G18 -> 0.05 | H28: =H27/H18 -> 0.05 | I28: =I27/I18 -> 0.05 | J28: =J27/J18 -> 0.05 | K28: =K27/K18 -> 0.05 | L28: =L27/L18 -> 0.05 | ... P28: =P27/P18 -> 0.05
A29: Imposto sobre o Faturamento | C29: Alíquota | D29: 0.16 | E29: 0.12798836 | F29: 0.13048797 | G29: 0.13235981 | H29: 0.13442758 | I29: 0.13623606 | J29: 0.13803785 | K29: 0.13997972 | L29: 0.14506742 | M29: 0.15081251 | N29: 0.15635105 | O29: 0.16086615 | P29: 0.16495483
A30: Imposto (prevista) | D30: 0.1
A31: Imposto Parcela 1 | D31: =D30 -> 0.1
A32: Imposto Parcela 2 | D32: =D31 -> 0.1
A33: Imposto Parcela 3 | D33: =D32 -> 0.1
A34: Imposto Parcela 4 | D34: =D33 -> 0.1
A35: Total Imposto (P1 + P2 + P3 + P4) | D35: =D34 -> 0.1
A36: Custo de Serviço Prestado | D36: =((180)+(675/5)+700/10+500/10) -> 435 | E36: =$D$36*E11 -> 3480 | F36: =$D$36*F11 -> 4176 | G36: =$D$36*G11 -> 5568 | H36: =$D$36*H11 -> 6124.8 | I36: =$D$36*I11 -> 6681.6 | J36: =$D$36*J11 -> 7238.4 | K36: =$D$36*K11 -> 7795.2 | L36: =$D$36*L11 -> 8352 | ... P36: =$D$36*P11 -> 8352
D37: % | E37: =E36/E18 -> 0.21964982 | F37: =F36/F18 -> 0.11152833 | G37: =G36/G18 -> 0.084053657 | H37: =H36/H18 -> 0.060376525 | I37: =I36/I18 -> 0.053883871 | J37: =J36/J18 -> 0.048855292 | K37: =K36/K18 -> 0.046223909 | L37: =L36/L18 -> 0.043718593 | ... P37: =P36/P18 -> 0.0348
A38: Margem de Lucro % (custo, comissão, imposto) | C38: 0.4 | D38: 0.62 | E38: =100%-E37-E28-E29 -> 0.60236181 | F38: =100%-F37-F28-F29 -> 0.70798369 | G38: =100%-G37-G28-G29 -> 0.73358653 | H38: =100%-H37-H28-H29 -> 0.75519589 | I38: =100%-I37-I28-I29 -> 0.75988007 | J38: =100%-J37-J28-J29 -> 0.76310686 | K38: =100%-K37-K28-K29 -> 0.76379637 | L38: =100%-L37-L28-L29 -> 0.76121399 | ... P38: =100%-P37-P28-P29 -> 0.75024517
A39: Lucro Bruto Oper/Serviço | B39: =SUM(E39:P39) -> 1596452.8 | C39: =AVERAGE(E39:P39) -> 133037.73 | D39: =D38*D13 -> 6609.2878 | E39: =E38*E13 -> 38173.837 | F39: =F38*F13 -> 61169.791 | G39: =G38*G13 -> 84509.168 | H39: =H38*H13 -> 106331.58 | I39: =I38*I13 -> 116717.58 | J39: =J38*J13 -> 139679.08 | K39: =K38*K13 -> 150559.54 | ... P39: =P38*P13 -> 172856.49
A40: Margens dos Projetos | B40: % | C40: Qtd. Mensal | D40: 1 parcela | E40: =E39/4 -> 9543.4591 | F40: =F39/4 -> 15292.448 | G40: =G39/4 -> 21127.292 | H40: =H39/4 -> 26582.895 | I40: =I39/4 -> 29179.395 | J40: =J39/4 -> 34919.77 | K40: =K39/4 -> 37639.885 | L40: =L39/4 -> 43845.926 | ... P40: =P39/4 -> 43214.122
A41: Disponibilidade | B41: =5125/8000 -> 0.640625 | C41: =3*4.28 -> 12.84 | D41: 2 parcela | E41: 0 | F41: =E40 -> 9543.4591 | G41: =F40 -> 15292.448 | H41: =G40 -> 21127.292 | I41: =H40 -> 26582.895 | J41: =I40 -> 29179.395 | K41: =J40 -> 34919.77 | L41: =K40 -> 37639.885 | M41: =L40 -> 43845.926 | ... P41: =O40 -> 43449.63
A42: Projeto | B42: =0.55 -> 0.55 | D42: 3 parcela | E42: 0 | G42: =F41 -> 9543.4591 | H42: =G41 -> 15292.448 | I42: =H41 -> 21127.292 | J42: =I41 -> 26582.895 | K42: =J41 -> 29179.395 | L42: =K41 -> 34919.77 | M42: =L41 -> 37639.885 | N42: =M41 -> 43845.926 | ... P42: =O41 -> 47773.076
A43: Laudo + G. Risco | B43: =59% -> 0.59 | D43: 4 parcela | E43: 0 | H43: =G42 -> 9543.4591 | I43: =H42 -> 15292.448 | J43: =I42 -> 21127.292 | K43: =J42 -> 26582.895 | L43: =K42 -> 29179.395 | M43: =L42 -> 34919.77 | N43: =M42 -> 37639.885 | O43: =N42 -> 43845.926 | P43: =O42 -> 46545.294
D44: Total Lucro Bruto Novo | E44: =SUM(E40:E43) -> 9543.4591 | F44: =SUM(F40:F43) -> 24835.907 | G44: =SUM(G40:G43) -> 45963.199 | H44: =SUM(H40:H43) -> 72546.094 | I44: =SUM(I40:I43) -> 92182.03 | J44: =SUM(J40:J43) -> 111809.35 | K44: =SUM(K40:K43) -> 128321.95 | L44: =SUM(L40:L43) -> 145584.98 | ... P44: =SUM(P40:P43) -> 180982.12
B45: =B48/B13 -> 0.81780862 | D45: Lucro previsto 2025 | E45: 58000 | F45: 39000 | G45: 25000 | H45: 5500
A47: Faturamento XPE | B47: =SUM(E47:P47) -> 2295717 | D47: 28000 | E47: =SUM(E44:E45)/E38+$D$47 -> 140131.04 | F47: =SUM(F44:F45)/F38+$D$47 -> 118165.79 | G47: =SUM(G44:G45)/G38+$D$47 -> 124734.6 | H47: =SUM(H44:H45)/H38+$D$47 -> 131345.5 | I47: =SUM(I44:I45)/I38+$D$47 -> 149311.29 | J47: =SUM(J44:J45)/J38+$D$47 -> 174518.6 | K47: =SUM(K44:K45)/K38+$D$47 -> 196005.44 | L47: =SUM(L44:L45)/L38+$D$47 -> 219253.68 | ... P47: =SUM(P44:P45)/P38+$D$47 -> 269230.64
A48: Margem de Contribuição Prevista | B48: =SUM(E48:P48) -> 1741878.1 | C48: Receita BRA + outros | D48: =28000*0.84 -> 23520 | E48: =$D$48+E45+E44 -> 91063.459 | F48: =$D$48+F45+F44 -> 87355.907 | G48: =$D$48+G45+G44 -> 94483.199 | H48: =$D$48+H45+H44 -> 101566.09 | I48: =$D$48+I45+I44 -> 115702.03 | J48: =$D$48+J45+J44 -> 135329.35 | K48: =$D$48+K45+K44 -> 151841.95 | L48: =$D$48+L45+L44 -> 169104.98 | ... P48: =$D$48+P45+P44 -> 204502.12
A49: Custo Fixo Total | B49: ='Premissas gerais'!B99 -> 85921 | E49: =B49 -> 85921 | F49: =E49 -> 85921 | G49: =F49 -> 85921 | H49: =G49 -> 85921 | I49: =H49 -> 85921 | J49: =I49 -> 85921 | K49: =J49 -> 85921 | L49: =K49 -> 85921 | M49: =L49 -> 85921 | ... P49: =O49 -> 85921
A50: Lucro Líquido Mensal | C50: =D51/B47 -> 0.3096314 | D50: =AVERAGE(E50:P50) -> 59235.505 | E50: =E48-E49 -> 5142.4591 | F50: =F48-F49 -> 1434.9069 | G50: =G48-G49 -> 8562.1989 | H50: =H48-H49 -> 15645.094 | I50: =I48-I49 -> 29781.03 | J50: =J48-J49 -> 49408.352 | K50: =K48-K49 -> 65920.945 | L50: =L48-L49 -> 83183.975 | ... P50: =P48-P49 -> 118581.12
A51: Lucro Líquido Acumulado | D51: =P51 -> 710826.06 | E51: =E50+C51 -> 5142.4591 | F51: =F50+E51 -> 6577.3661 | G51: =G50+F51 -> 15139.565 | H51: =H50+G51 -> 30784.659 | I51: =I50+H51 -> 60565.689 | J51: =J50+I51 -> 109974.04 | K51: =K50+J51 -> 175894.99 | L51: =L50+K51 -> 259078.96 | M51: =M50+L51 -> 359628.84 | ... P51: =P50+O51 -> 710826.06
A55: MRR - Plataforma | E55: 0 | F55: 0 | G55: 1
A56: Ticket médio | D56: 100 | E56: =D56 -> 100 | F56: =E56 -> 100 | G56: =F56 -> 100 | H56: =G56 -> 100 | I56: =H56 -> 100 | J56: =I56 -> 100 | K56: =J56 -> 100 | L56: =K56 -> 100 | ... P56: =O56 -> 100
A57: Taxa de conversão | D57: 0.2 | E57: =D57 -> 0.2 | F57: =E57 -> 0.2 | G57: =F57 -> 0.2 | H57: =G57 -> 0.2 | I57: =H57 -> 0.2 | J57: =I57 -> 0.2 | K57: =J57 -> 0.2 | L57: =K57 -> 0.2 | ... P57: =O57 -> 0.2
A58: qtd. Novos clientes | E58: =E57*E11 -> 1.6 | F58: =F57*F11 -> 1.92 | G58: =G57*G11 -> 2.56 | H58: =H57*H11 -> 2.816 | I58: =I57*I11 -> 3.072 | J58: =J57*J11 -> 3.328 | K58: =K57*K11 -> 3.584 | L58: =L57*L11 -> 3.84 | ... P58: =P57*P11 -> 3.84
A59: Acumulado de Clientes | D59: 03 meses sem plataforma | E59: 0 | F59: 0 | G59: 0 | H59: =H58+G59 -> 2.816 | I59: =I58+H59 -> 5.888 | J59: =J58+I59 -> 9.216 | K59: =K58+J59 -> 12.8 | L59: =L58+K59 -> 16.64 | M59: =M58+L59 -> 20.736 | N59: =N58+M59 -> 24.96 | O59: =O58+N59 -> 28.8 | P59: =P58+O59 -> 32.64
A60: Faturamento Mensal | E60: =E59*E56 -> 0 | F60: =F59*F56 -> 0 | G60: =G59*G56 -> 0 | H60: =H59*H56 -> 281.6 | I60: =I59*I56 -> 588.8 | J60: =J59*J56 -> 921.6 | K60: =K59*K56 -> 1280 | L60: =L59*L56 -> 1664 | ... P60: =P59*P56 -> 3264
A61: Acumulado anual | E61: =E60 -> 0 | F61: =F60+E61 -> 0 | G61: =G60+F61 -> 0 | H61: =H60+G61 -> 281.6 | I61: =I60+H61 -> 870.4 | J61: =J60+I61 -> 1792 | K61: =K60+J61 -> 3072 | L61: =L60+K61 -> 4736 | M61: =M60+L61 -> 6809.6 | ... P61: =P60+O61 -> 15449.6
A64: MRR - Ger. Carregadores Ticket | D64: 200 | E64: =D64 -> 200 | F64: =E64 -> 200 | G64: =F64 -> 200 | H64: =G64 -> 200 | I64: =H64 -> 200 | J64: =I64 -> 200 | K64: =J64 -> 200 | L64: =K64 -> 200 | ... P64: =O64 -> 200
A65: Taxa de conversão | D65: 0.1 | E65: =D65 -> 0.1 | F65: =E65 -> 0.1 | G65: =F65 -> 0.1 | H65: =G65 -> 0.1 | I65: =H65 -> 0.1 | J65: =I65 -> 0.1 | K65: =J65 -> 0.1 | L65: =K65 -> 0.1 | ... P65: =O65 -> 0.1
A66: qtd. Novos clientes | E66: =E65*E11 -> 0.8 | F66: =F65*F11 -> 0.96 | G66: =G65*G11 -> 1.28 | H66: =H65*H11 -> 1.408 | I66: =I65*I11 -> 1.536 | J66: =J65*J11 -> 1.664 | K66: =K65*K11 -> 1.792 | L66: =L65*L11 -> 1.92 | ... P66: =P65*P11 -> 1.92
A67: Acumulado de Clientes | E67: 0 | F67: 0 | G67: 0 | H67: 0 | I67: 0 | J67: =J66+I67 -> 1.664 | K67: =K66+J67 -> 3.456 | L67: =L66+K67 -> 5.376 | M67: =M66+L67 -> 7.424 | N67: =N66+M67 -> 9.536 | O67: =O66+N67 -> 11.456 | P67: =P66+O67 -> 13.376
A68: Faturamento Mensal | E68: =B67*B64 -> 0 | F68: =C67*C64 -> 0 | G68: =D67*D64 -> 0 | H68: =E67*E64 -> 0 | I68: =F67*F64 -> 0 | J68: =J67*J64 -> 332.8 | K68: =K67*K64 -> 691.2 | L68: =L67*L64 -> 1075.2 | M68: =M67*M64 -> 1484.8 | N68: =N67*N64 -> 1907.2 | O68: =O67*O64 -> 2291.2 | P68: =P67*P64 -> 2675.2
A69: Acumulado anual | E69: =E68 -> 0 | F69: =F68 -> 0 | G69: =G68 -> 0 | H69: =H68 -> 0 | I69: =I68+H69 -> 0 | J69: =J68+I69 -> 332.8 | K69: =K68+J69 -> 1024 | L69: =L68+K69 -> 2099.2 | M69: =M68+L69 -> 3584 | N69: =N68+M69 -> 5491.2 | O69: =O68+N69 -> 7782.4 | P69: =P68+O69 -> 10457.6
A70: Setup | D70: =3000+3*1500+5000 -> 12500 | J70: =$D$70*J66 -> 20800 | K70: =$D$70*K66 -> 22400 | L70: =$D$70*L66 -> 24000 | M70: =$D$70*M66 -> 25600 | N70: =$D$70*N66 -> 26400 | O70: =$D$70*O66 -> 24000 | P70: =$D$70*P66 -> 24000
A71: Parcela 1 | J71: =J70/2 -> 10400 | K71: =K70/2 -> 11200 | L71: =L70/2 -> 12000 | M71: =M70/2 -> 12800 | N71: =N70/2 -> 13200 | O71: =O70/2 -> 12000 | P71: =P70/2 -> 12000
A72: Parcela 2 | K72: =J71 -> 10400 | L72: =K71 -> 11200 | M72: =L71 -> 12000 | N72: =M71 -> 12800 | O72: =N71 -> 13200 | P72: =O71 -> 12000
A73: Total Parcelas | J73: =SUM(J71:J72) -> 10400 | K73: =SUM(K71:K72) -> 21600 | L73: =SUM(L71:L72) -> 23200 | M73: =SUM(M71:M72) -> 24800 | N73: =SUM(N71:N72) -> 26000 | O73: =SUM(O71:O72) -> 25200 | P73: =SUM(P71:P72) -> 24000
A74: % Setup | D74: 0.5 | E74: =$D74*E70 -> 0 | F74: =$D74*F70 -> 0 | G74: =$D74*G70 -> 0 | H74: =$D74*H70 -> 0 | I74: =$D74*I70 -> 0 | J74: =$D74*J70 -> 10400 | K74: =$D74*K70 -> 11200 | L74: =$D74*L70 -> 12000 | ... P74: =$D74*P70 -> 12000
A75: % MRR Hard | D75: 0.7 | E75: =$D75*E68 -> 0 | F75: =$D75*F68 -> 0 | G75: =$D75*G68 -> 0 | H75: =$D75*H68 -> 0 | I75: =$D75*I68 -> 0 | J75: =$D75*J68 -> 232.96 | K75: =$D75*K68 -> 483.84 | L75: =$D75*L68 -> 752.64 | ... P75: =$D75*P68 -> 1872.64
A76: % MRR Plataforma | D76: 0.75 | E76: =$D76*E60 -> 0 | F76: =$D76*F60 -> 0 | G76: =$D76*G60 -> 0 | H76: =$D76*H60 -> 211.2 | I76: =$D76*I60 -> 441.6 | J76: =$D76*J60 -> 691.2 | K76: =$D76*K60 -> 960 | L76: =$D76*L60 -> 1248 | ... P76: =$D76*P60 -> 2448
A77: Faturamento Total Plat. + Smart C | C77: =SUM(E77:P77) -> 193107.2 | D77: =AVERAGE(E77:P77) -> 16092.267 | E77: =E70+E68+E60 -> 0 | F77: =F70+F68+F60 -> 0 | G77: =G70+G68+G60 -> 0 | H77: =H70+H68+H60 -> 281.6 | I77: =I70+I68+I60 -> 588.8 | J77: =J70+J68+J60 -> 22054.4 | K77: =K70+K68+K60 -> 24371.2 | L77: =L70+L68+L60 -> 26739.2 | ... P77: =P70+P68+P60 -> 29939.2
A78: Margem de Contrib Total tec | C78: =SUM(E78:P78) -> 102507.52 | D78: =AVERAGE(E78:P78) -> 8542.2933 | E78: =E76+E75+E74 -> 0 | F78: =F76+F75+F74 -> 0 | G78: =G76+G75+G74 -> 0 | H78: =H76+H75+H74 -> 211.2 | I78: =I76+I75+I74 -> 441.6 | J78: =J76+J75+J74 -> 11324.16 | K78: =K76+K75+K74 -> 12643.84 | L78: =L76+L75+L74 -> 14000.64 | ... P78: =P76+P75+P74 -> 16320.64
A81: Faturamento Obras
A82: Qtd de Consultorias Mês | B82: Total | C82: Qtd | D82: Taxa
A83: Margem | B83: 110000 | C83: 6 | D83: 0.13
A84: Qtd de Obras Previstas | D84: Ticket | E84: =$D$83*E11 -> 1.04 | F84: =$D$83*F11 -> 1.248 | G84: =$D$83*G11 -> 1.664 | H84: =$D$83*H11 -> 1.8304 | I84: =$D$83*I11 -> 1.9968 | J84: =$D$83*J11 -> 2.1632 | K84: =$D$83*K11 -> 2.3296 | L84: =$D$83*L11 -> 2.496 | ... P84: =$D$83*P11 -> 2.496
A85: Faturamento previsto | B85: Faturamento total | C85: =SUM(E85:P85) -> 461413.33 | D85: =B83/C83 -> 18333.333 | E85: =E84*$D$85 -> 19066.667 | F85: =F84*$D$85 -> 22880 | G85: =G84*$D$85 -> 30506.667 | H85: =H84*$D$85 -> 33557.333 | I85: =I84*$D$85 -> 36608 | J85: =J84*$D$85 -> 39658.667 | K85: =K84*$D$85 -> 42709.333 | L85: =L84*$D$85 -> 45760 | ... P85: =P84*$D$85 -> 45760
A86: Parcela 1 | E86: =E85/4 -> 4766.6667 | F86: =F85/4 -> 5720 | G86: =G85/4 -> 7626.6667 | H86: =H85/4 -> 8389.3333 | I86: =I85/4 -> 9152 | J86: =J85/4 -> 9914.6667 | K86: =K85/4 -> 10677.333 | L86: =L85/4 -> 11440 | ... P86: =P85/4 -> 11440
A87: Parcela 2 | F87: =E86 -> 4766.6667 | G87: =F86 -> 5720 | H87: =G86 -> 7626.6667 | I87: =H86 -> 8389.3333 | J87: =I86 -> 9152 | K87: =J86 -> 9914.6667 | L87: =K86 -> 10677.333 | M87: =L86 -> 11440 | ... P87: =O86 -> 11440
A88: Parcela 3 | G88: =F87 -> 4766.6667 | H88: =G87 -> 5720 | I88: =H87 -> 7626.6667 | J88: =I87 -> 8389.3333 | K88: =J87 -> 9152 | L88: =K87 -> 9914.6667 | M88: =L87 -> 10677.333 | N88: =M87 -> 11440 | ... P88: =O87 -> 12584
A89: Parcela 4 | H89: =G88 -> 4766.6667 | I89: =H88 -> 5720 | J89: =I88 -> 7626.6667 | K89: =J88 -> 8389.3333 | L89: =K88 -> 9152 | M89: =L88 -> 9914.6667 | N89: =M88 -> 10677.333 | O89: =N88 -> 11440 | P89: =O88 -> 12202.667
A90: Total Recebido | E90: =SUM(E86:E89) -> 4766.6667 | F90: =SUM(F86:F89) -> 10486.667 | G90: =SUM(G86:G89) -> 18113.333 | H90: =SUM(H86:H89) -> 26502.667 | I90: =SUM(I86:I89) -> 30888 | J90: =SUM(J86:J89) -> 35082.667 | K90: =SUM(K86:K89) -> 38133.333 | L90: =SUM(L86:L89) -> 41184 | ... P90: =SUM(P86:P89) -> 47666.667
A91: Custo Inicial | D91: 0.45 | E91: =E85*$D$91 -> 8580 | F91: =F85*$D$91 -> 10296 | G91: =G85*$D$91 -> 13728 | H91: =H85*$D$91 -> 15100.8 | I91: =I85*$D$91 -> 16473.6 | J91: =J85*$D$91 -> 17846.4 | K91: =K85*$D$91 -> 19219.2 | L91: =L85*$D$91 -> 20592 | ... P91: =P85*$D$91 -> 20592
A92: Saldo Real (caixa disponivel) | E92: =E90-E91 -> -3813.3333 | F92: =F90-F91 -> 190.66667 | G92: =G90-G91 -> 4385.3333 | H92: =H90-H91 -> 11401.867 | I92: =I90-I91 -> 14414.4 | J92: =J90-J91 -> 17236.267 | K92: =K90-K91 -> 18914.133 | L92: =L90-L91 -> 20592 | ... P92: =P90-P91 -> 27074.667
A93: Saldo Acumulado | B93: Receita total | C93: =P93 -> 183993.33 | E93: =E92 -> -3813.3333 | F93: =F92+E93 -> -3622.6667 | G93: =G92+F93 -> 762.66667 | H93: =H92+G93 -> 12164.533 | I93: =I92+H93 -> 26578.933 | J93: =J92+I93 -> 43815.2 | K93: =K92+J93 -> 62729.333 | L93: =L92+K93 -> 83321.333 | M93: =M92+L93 -> 105591.2 | ... P93: =P92+O93 -> 183993.33
A94: Lucro Real | D94: 0.35 | H94: =$D$94*E85 -> 6673.3333 | I94: =$D$94*F85 -> 8008 | J94: =$D$94*G85 -> 10677.333 | K94: =$D$94*H85 -> 11745.067 | L94: =$D$94*I85 -> 12812.8 | M94: =$D$94*J85 -> 13880.533 | N94: =$D$94*K85 -> 14948.267 | O94: =$D$94*L85 -> 16016 | P94: =$D$94*M85 -> 17083.733
A95: Margem Contribuição Obras | D95: 0.42 | E95: =E85*$D$95 -> 8008 | F95: =F85*$D$95 -> 9609.6 | G95: =G85*$D$95 -> 12812.8 | H95: =H85*$D$95 -> 14094.08 | I95: =I85*$D$95 -> 15375.36 | J95: =J85*$D$95 -> 16656.64 | K95: =K85*$D$95 -> 17937.92 | L95: =L85*$D$95 -> 19219.2 | ... P95: =P85*$D$95 -> 19219.2
A96: p1 | E96: 0 | F96: =E95*1/3 -> 2669.3333 | G96: =F95*1/3 -> 3203.2 | H96: =G95*1/3 -> 4270.9333 | I96: =H95*1/3 -> 4698.0267 | J96: =I95*1/3 -> 5125.12 | K96: =J95*1/3 -> 5552.2133 | L96: =K95*1/3 -> 5979.3067 | M96: =L95*1/3 -> 6406.4 | ... P96: =O95*1/3 -> 6406.4
A97: Faturamento Total Global | B97: =SUM(E97:P97) -> 3411650.8 | C97: média | D97: =AVERAGE(E97:P97) -> 284304.24 | E97: =E85+E103 -> 178264.38 | F97: =F85+F103 -> 163925.79 | G97: =G85+G103 -> 185747.93 | H97: =H85+H103 -> 198741.76 | I97: =I85+I103 -> 223116.09 | J97: =J85+J103 -> 275890.34 | K97: =K85+K103 -> 305795.31 | L97: =L85+L103 -> 337512.88 | ... P97: =P85+P103 -> 390689.84
A98: p2 | G98: =F96 -> 2669.3333 | H98: =G96 -> 3203.2 | I98: =H96 -> 4270.9333 | J98: =I96 -> 4698.0267 | K98: =J96 -> 5125.12 | L98: =K96 -> 5552.2133 | M98: =L96 -> 5979.3067 | N98: =M96 -> 6406.4 | ... P98: =O96 -> 7047.04
A99: p3 | H99: =G98 -> 2669.3333 | I99: =H98 -> 3203.2 | J99: =I98 -> 4270.9333 | K99: =J98 -> 4698.0267 | L99: =K98 -> 5125.12 | M99: =L98 -> 5552.2133 | N99: =M98 -> 5979.3067 | O99: =N98 -> 6406.4 | P99: =O98 -> 6833.4933
A100: Total Recebido | E100: =E99+E98+E96 -> 0 | F100: =F99+F98+F96 -> 2669.3333 | G100: =G99+G98+G96 -> 5872.5333 | H100: =H99+H98+H96 -> 10143.467 | I100: =I99+I98+I96 -> 12172.16 | J100: =J99+J98+J96 -> 14094.08 | K100: =K99+K98+K96 -> 15375.36 | L100: =L99+L98+L96 -> 16656.64 | ... P100: =P99+P98+P96 -> 20286.933
C102: Total | D102: Média | E102: =E84+E11 -> 9.04 | F102: =F84+F11 -> 10.848 | G102: =G84+G11 -> 14.464
A103: Fatutamento XPE Global | C103: =SUM(E103:P103) -> 2950237.5 | D103: =AVERAGE(E103:P103) -> 245853.12 | E103: =E77+E85+E47 -> 159197.71 | F103: =F77+F85+F47 -> 141045.79 | G103: =G77+G85+G47 -> 155241.27 | H103: =H77+H85+H47 -> 165184.43 | I103: =I77+I85+I47 -> 186508.09 | J103: =J77+J85+J47 -> 236231.67 | K103: =K77+K85+K47 -> 263085.97 | L103: =L77+L85+L47 -> 291752.88 | ... P103: =P77+P85+P47 -> 344929.84
A104: Margem LL XPE Global | B104: =C104/C103 -> 0.3281255 | C104: =SUM(E104:P104) -> 968048.14 | D104: =AVERAGE(E104:P104) -> 80670.679 | E104: =E100+E78+E50 -> 5142.4591 | F104: =F100+F78+F50 -> 4104.2402 | G104: =G100+G78+G50 -> 14434.732 | H104: =H100+H78+H50 -> 25999.761 | I104: =I100+I78+I50 -> 42394.79 | J104: =J100+J78+J50 -> 74826.592 | K104: =K100+K78+K50 -> 93940.145 | L104: =L100+L78+L50 -> 113841.26 | ... P104: =P100+P78+P50 -> 155188.69
A105: CONTRATO FECHADO - Consult. + Obras | C105: =SUM(E105:P105) -> 2591346.9 | D105: =AVERAGE(E105:P105) -> 215945.58 | E105: =E13+E85 -> 82440.267 | F105: =F13+F85 -> 109280 | G105: =G13+G85 -> 145706.67 | H105: =H13+H85 -> 174357.33 | I105: =I13+I85 -> 190208 | J105: =J13+J85 -> 222698.67 | K105: =K13+K85 -> 239829.33 | L105: =L13+L85 -> 276160 | ... P105: =P13+P85 -> 276160
E106: =SUM(E105:G105) -> 337426.93 | H106: =SUM(H105:J105) -> 587264 | K106: =SUM(K105:M105) -> 810560 | N106: =SUM(N105:P105) -> 856096
E108: =10%*E103 -> 15919.771 | F108: =10%*F103 -> 14104.579 | G108: =10%*G103 -> 15524.127 | H108: =10%*H103 -> 16518.443 | I108: =10%*I103 -> 18650.809 | J108: =10%*J103 -> 23623.167 | K108: =10%*K103 -> 26308.597 | L108: =10%*L103 -> 29175.288 | ... P108: =10%*P103 -> 34492.984
C109: 5000 | D109: Fixo | E109: =$C$109*E5 -> 10000 | F109: =$C$109*F5 -> 10000 | G109: =$C$109*G5 -> 10000 | H109: =$C$109*H5 -> 10000 | I109: =$C$109*I5 -> 10000 | J109: =$C$109*J5 -> 10000 | K109: =$C$109*K5 -> 10000 | L109: =$C$109*L5 -> 10000 | ... P109: =$C$109*P5 -> 10000
D110: qtd vendas por vendedor | E110: =(E84+E66+E11)/E5 -> 4.92 | F110: =(F84+F66+F11)/F5 -> 5.904 | G110: =(G84+G66+G11)/G5 -> 7.872 | H110: =(H84+H66+H11)/H5 -> 8.6592 | I110: =(I84+I66+I11)/I5 -> 9.4464 | J110: =(J84+J66+J11)/J5 -> 10.2336 | K110: =(K84+K66+K11)/K5 -> 11.0208 | L110: =(L84+L66+L11)/L5 -> 11.808 | ... P110: =(P84+P66+P11)/P5 -> 11.808
...

Sheet Projeção Projetos Joni
A1: Projetos Consultoria
A2: Mês | E2: Total | F2: Média | H2: Referência | I2: 1 | J2: 2 | K2: 3 | L2: 4 | M2: 5 | N2: 6 | O2: 7 | P2: 8 | Q2: 9 | R2: 10 | S2: 11 | T2: 12
A3: Total de Fechamentos | E3: ='Projeção Biel Ajustada'!B11 -> 193.6 | F3: ='Projeção Biel Ajustada'!C11 -> 15.507692 | H3: ='Projeção Biel Ajustada'!D11 -> 8 | I3: ='Projeção Biel Ajustada'!E11 -> 8 | J3: ='Projeção Biel Ajustada'!F11 -> 9.6 | K3: ='Projeção Biel Ajustada'!G11 -> 12.8 | L3: ='Projeção Biel Ajustada'!H11 -> 14.08 | M3: ='Projeção Biel Ajustada'!I11 -> 15.36 | N3: ='Projeção Biel Ajustada'!J11 -> 16.64 | O3: ='Projeção Biel Ajustada'!K11 -> 17.92 | ... T3: ='Projeção Biel Ajustada'!P11 -> 19.2
A4: Ticket médio | H4: ='Projeção Biel Ajustada'!E10 -> 0.32 | I4: 9000 | J4: 9000 | K4: 9000 | L4: 9000 | M4: 9000 | N4: 9000 | O4: 9000 | P4: 9000 | Q4: 9000 | R4: 9000 | S4: 9000 | T4: 9000
A5: Acumulado de Negócios | H5: 1 | I5: =I3 -> 8 | J5: =J3+I5 -> 17.6 | K5: =K3+J5 -> 30.4 | L5: =L3+K5 -> 44.48 | M5: =M3+L5 -> 59.84 | N5: =N3+M5 -> 76.48 | O5: =O3+N5 -> 94.4 | P5: =P3+O5 -> 113.6 | Q5: =Q3+P5 -> 134.08 | ... T5: =T3+S5 -> 193.6
A6: Serviços | I6: =I4*I3/$B$15 -> 9.7156627 | J6: =J4*J3/$B$15 -> 11.658795 | K6: =K4*K3/$B$15 -> 15.54506 | L6: =L4*L3/$B$15 -> 17.099566 | M6: =M4*M3/$B$15 -> 18.654072 | N6: =N4*N3/$B$15 -> 20.208578 | O6: =O4*O3/$B$15 -> 21.763084 | P6: =P4*P3/$B$15 -> 23.31759 | ... T6: =T4*T3/$B$15 -> 23.31759
A7: Serviços Acumulados | I7: =I6 -> 9.7156627 | J7: =I7+J6 -> 21.374458 | K7: =J7+K6 -> 36.919518 | L7: =K7+L6 -> 54.019084 | M7: =L7+M6 -> 72.673157 | N7: =M7+N6 -> 92.881735 | O7: =N7+O6 -> 114.64482 | P7: =O7+P6 -> 137.96241 | Q7: =P7+Q6 -> 162.83451 | ... T7: =S7+T6 -> 235.11904
A8: Custo de Serviço Prestado | B8: TICKET | C8: Taxa de QNTD | D8: PREPARAÇÃO | E8: TEMPO CAMPO (DIAS) | F8: TEMPO PROJETO (DIAS) | G8: TEMPO REVISÃO (DIAS) | H8: TICKET/TEMPO
A9: Disponibilidade Carga + PE | B9: 9000 | C9: =27/56 -> 0.48214286 | D9: 3 | E9: 6 | F9: 2 | G9: 1 | H9: =B9/SUM(D9:G9) -> 750 | I9: =$C9*I$6 -> 4.6843373 | J9: =$C9*J$6 -> 5.6212048 | K9: =$C9*K$6 -> 7.4949398 | L9: =$C9*L$6 -> 8.2444337 | M9: =$C9*M$6 -> 8.9939277 | N9: =$C9*N$6 -> 9.7434217 | O9: =$C9*O$6 -> 10.492916 | P9: =$C9*P$6 -> 11.24241 | ... T9: =$C9*T$6 -> 11.24241
A10: Laudo Instalações + G. Risco | B10: 7000 | C10: =15/56 -> 0.26785714 | D10: 3 | E10: 1 | F10: 5 | G10: 2 | H10: =B10/SUM(D10:G10) -> 636.36364 | I10: =$C10*I$6 -> 2.6024096 | J10: =$C10*J$6 -> 3.1228916 | K10: =$C10*K$6 -> 4.1638554 | L10: =$C10*L$6 -> 4.580241 | M10: =$C10*M$6 -> 4.9966265 | N10: =$C10*N$6 -> 5.413012 | O10: =$C10*O$6 -> 5.8293976 | P10: =$C10*P$6 -> 6.2457831 | ... T10: =$C10*T$6 -> 6.2457831
A11: Inspeção Carregadores (+/- 5 unid) | B11: 2500 | C11: =4/56 -> 0.071428571 | D11: 3 | E11: 1 | F11: 1 | G11: 1 | H11: =B11/SUM(D11:G11) -> 416.66667 | I11: =$C11*I$6 -> 0.6939759 | J11: =$C11*J$6 -> 0.83277108 | K11: =$C11*K$6 -> 1.1103614 | L11: =$C11*L$6 -> 1.2213976 | M11: =$C11*M$6 -> 1.3324337 | N11: =$C11*N$6 -> 1.4434699 | O11: =$C11*O$6 -> 1.554506 | P11: =$C11*P$6 -> 1.6655422 | ... T11: =$C11*T$6 -> 1.6655422
A12: Projeto CDM | B12: 5000 | C12: =4/56 -> 0.071428571 | D12: 3 | E12: 1 | F12: 5 | G12: 2 | H12: =B12/SUM(D12:G12) -> 454.54545 | I12: =$C12*I$6 -> 0.6939759 | J12: =$C12*J$6 -> 0.83277108 | K12: =$C12*K$6 -> 1.1103614 | L12: =$C12*L$6 -> 1.2213976 | M12: =$C12*M$6 -> 1.3324337 | N12: =$C12*N$6 -> 1.4434699 | O12: =$C12*O$6 -> 1.554506 | P12: =$C12*P$6 -> 1.6655422 | ... T12: =$C12*T$6 -> 1.6655422
A13: Projeto Eletrocalha + Botão | B13: 5000 | C13: =5/56 -> 0.089285714 | D13: 3 | E13: 2 | F13: 15 | G13: 2 | H13: =B13/SUM(D13:G13) -> 227.27273 | I13: =$C13*I$6 -> 0.86746988 | J13: =$C13*J$6 -> 1.0409639 | K13: =$C13*K$6 -> 1.3879518 | L13: =$C13*L$6 -> 1.526747 | M13: =$C13*M$6 -> 1.6655422 | N13: =$C13*N$6 -> 1.8043373 | O13: =$C13*O$6 -> 1.9431325 | P13: =$C13*P$6 -> 2.0819277 | ... T13: =$C13*T$6 -> 2.0819277
A14: Laudo SPDA + Viabilidade Estr. + Proj | B14: 12000 | C14: =1/56 -> 0.017857143 | D14: 3 | E14: 8 | F14: 15 | G14: 2 | H14: =B14/SUM(D14:G14) -> 428.57143 | I14: =$C14*I$6 -> 0.17349398 | J14: =$C14*J$6 -> 0.20819277 | K14: =$C14*K$6 -> 0.27759036 | L14: =$C14*L$6 -> 0.3053494 | M14: =$C14*M$6 -> 0.33310843 | N14: =$C14*N$6 -> 0.36086747 | O14: =$C14*O$6 -> 0.38862651 | P14: =$C14*P$6 -> 0.41638554 | ... T14: =$C14*T$6 -> 0.41638554
B15: =SUMPRODUCT(B9:B14,C9:C14) -> 7410.7143 | C15: =SUM(C9:C14) -> 1
A16: Custo de Serviço Prestado | B16: TICKET | C16: Taxa de QNTD | D16: PREPARAÇÃO | E16: CAPACIDADE CAMPO | F16: CAPACIDADE PROJETO | G16: TEMPO REVISÃO (DIAS) | H16: OUTROS (DIAS)
A17: Disponibilidade Carga | B17: 9000 | C17: =27/56 -> 0.48214286 | D17: 3 | E17: =20/E9*4 -> 13.333333 | F17: =20/F9 -> 10 | G17: =20/G9 -> 20 | I17: =$C17*I$6 -> 4.6843373 | J17: =$C17*J$6 -> 5.6212048 | K17: =$C17*K$6 -> 7.4949398 | L17: =$C17*L$6 -> 8.2444337 | M17: =$C17*M$6 -> 8.9939277 | N17: =$C17*N$6 -> 9.7434217 | O17: =$C17*O$6 -> 10.492916 | P17: =$C17*P$6 -> 11.24241 | ... T17: =$C17*T$6 -> 11.24241
A18: Laudo Instalações + G. Risco | B18: 7000 | C18: =15/56 -> 0.26785714 | D18: 3 | E18: =20/E10 -> 20 | F18: =20/F10 -> 4 | G18: =20/G10 -> 10 | I18: =$C18*I$6 -> 2.6024096 | J18: =$C18*J$6 -> 3.1228916 | K18: =$C18*K$6 -> 4.1638554 | L18: =$C18*L$6 -> 4.580241 | M18: =$C18*M$6 -> 4.9966265 | N18: =$C18*N$6 -> 5.413012 | O18: =$C18*O$6 -> 5.8293976 | P18: =$C18*P$6 -> 6.2457831 | ... T18: =$C18*T$6 -> 6.2457831
A19: Inspeção Carregadores (+/- 5 unid) | B19: 2500 | C19: =4/56 -> 0.071428571 | D19: 3 | E19: =20/E11 -> 20 | F19: =20/F11 -> 20 | G19: =20/G11 -> 20 | I19: =$C19*I$6 -> 0.6939759 | J19: =$C19*J$6 -> 0.83277108 | K19: =$C19*K$6 -> 1.1103614 | L19: =$C19*L$6 -> 1.2213976 | M19: =$C19*M$6 -> 1.3324337 | N19: =$C19*N$6 -> 1.4434699 | O19: =$C19*O$6 -> 1.554506 | P19: =$C19*P$6 -> 1.6655422 | ... T19: =$C19*T$6 -> 1.6655422
A20: Projeto CDM | B20: 5000 | C20: =4/56 -> 0.071428571 | D20: 3 | E20: =20/E12 -> 20 | F20: =20/F12 -> 4 | G20: =20/G12 -> 10 | H20: 40 | I20: =$C20*I$6 -> 0.6939759 | J20: =$C20*J$6 -> 0.83277108 | K20: =$C20*K$6 -> 1.1103614 | L20: =$C20*L$6 -> 1.2213976 | M20: =$C20*M$6 -> 1.3324337 | N20: =$C20*N$6 -> 1.4434699 | O20: =$C20*O$6 -> 1.554506 | P20: =$C20*P$6 -> 1.6655422 | ... T20: =$C20*T$6 -> 1.6655422
A21: Projeto Eletrocalha | B21: 5000 | C21: =5/56 -> 0.089285714 | D21: 3 | E21: =20/E13 -> 10 | F21: =20/F13 -> 1.3333333 | G21: =20/G13 -> 10 | I21: =$C21*I$6 -> 0.86746988 | J21: =$C21*J$6 -> 1.0409639 | K21: =$C21*K$6 -> 1.3879518 | L21: =$C21*L$6 -> 1.526747 | M21: =$C21*M$6 -> 1.6655422 | N21: =$C21*N$6 -> 1.8043373 | O21: =$C21*O$6 -> 1.9431325 | P21: =$C21*P$6 -> 2.0819277 | ... T21: =$C21*T$6 -> 2.0819277
A22: Laudo SPDA + Viabilidade Estr. + Proj | B22: 12000 | C22: =1/56 -> 0.017857143 | D22: 3 | E22: =20/E14 -> 2.5 | F22: =20/F14 -> 1.3333333 | G22: =20/G14 -> 10 | I22: =$C22*I$6 -> 0.17349398 | J22: =$C22*J$6 -> 0.20819277 | K22: =$C22*K$6 -> 0.27759036 | L22: =$C22*L$6 -> 0.3053494 | M22: =$C22*M$6 -> 0.33310843 | N22: =$C22*N$6 -> 0.36086747 | O22: =$C22*O$6 -> 0.38862651 | P22: =$C22*P$6 -> 0.41638554 | ... T22: =$C22*T$6 -> 0.41638554
A24: CUSTO EXECUÇÃO / PESSOA | B24: /ANO | C24: /MES
A25: EPI | B25: 1000 | C25: =B25/12 -> 83.333333
A26: CALIBRAÇÃO | B26: 12000 | C26: =B26/12 -> 1000
A27: FERRAMENTA | B27: =(100*5+500+350+300+50+45+100*5*12)/5 -> 1549 | C27: =B27/12 -> 129.08333
A28: TOTAL | B28: =SUM(B25:B27) -> 14549 | C28: =B28/12 -> 1212.4167

Sheet Projeção Base
A1: Faturamento Consultoria
A2: Mês | B2: Total | C2: Média | D2: Referência | E2: 1 | F2: 2 | G2: 3 | H2: 4 | I2: 5 | J2: 6 | K2: 7 | L2: 8 | M2: 9 | N2: 10 | O2: 11 | P2: 12
A3: Curva Faturamento R$ | B3: =SUM(E3:P3) -> 2008800 | C3: =AVERAGE(E3:P3) -> 167400 | E3: ='Premissas gerais'!O5 -> 42943.468 | F3: ='Premissas gerais'!P5 -> 90658.432 | G3: ='Premissas gerais'!Q5 -> 26243.23 | H3: ='Premissas gerais'!R5 -> 181316.86 | I3: ='Premissas gerais'!S5 -> 152687.89 | J3: ='Premissas gerais'!T5 -> 183702.61 | K3: ='Premissas gerais'!U5 -> 167002.38 | L3: ='Premissas gerais'!V5 -> 250503.56 | ... P3: ='Premissas gerais'!Z5 -> 214717.34
A4: Curva Faturamento % | B4: 1 | C4: =AVERAGE(E4:P4) -> 1 | E4: =E3/$C$3 -> 0.25653207 | F4: =F3/$C$3 -> 0.5415677 | G4: =G3/$C$3 -> 0.1567696 | H4: =H3/$C$3 -> 1.0831354 | I4: =I3/$C$3 -> 0.91211401 | J4: =J3/$C$3 -> 1.0973872 | K4: =K3/$C$3 -> 0.9976247 | L4: =L3/$C$3 -> 1.4964371 | ... P4: =P3/$C$3 -> 1.2826603
A5: Qtd Vendedores | B5: =C5 -> 2 | C5: =AVERAGE(E5:P5) -> 2 | D5: 2 | E5: =D5 -> 2 | F5: =E5 -> 2 | G5: =F5 -> 2 | H5: =G5 -> 2 | I5: =H5 -> 2 | J5: =I5 -> 2 | K5: 2 | L5: =K5 -> 2 | M5: =L5 -> 2 | N5: =M5 -> 2 | O5: =N5 -> 2 | P5: =O5 -> 2
A6: Qtd Visita / Vendedor | B6: =SUM(E6:P6) -> 288.5 | C6: =AVERAGE(E6:P6) -> 24.041667 | D6: 12.5 | E6: =D6 -> 12.5 | F6: 15 | G6: 17 | H6: 20 | I6: 22 | J6: 25 | K6: 27 | L6: 30 | M6: =L6 -> 30 | N6: =M6 -> 30 | O6: =N6 -> 30 | P6: =O6 -> 30
A7: Total de Propostas | B7: =SUM(E7:P7) -> 577 | C7: =AVERAGE(E7:P7) -> 48.083333 | D7: =E6*E5 -> 25 | E7: =E5*E6 -> 25 | F7: =F5*F6 -> 30 | G7: =G5*G6 -> 34 | H7: =H5*H6 -> 40 | I7: =I5*I6 -> 44 | J7: =J5*J6 -> 50 | K7: =K5*K6 -> 54 | L7: =L5*L6 -> 60 | ... P7: =P5*P6 -> 60
A8: Taxa de Conversa Prop/Fech | B8: =SUM(E8:P8) -> 3.84 | C8: =AVERAGE(E8:P8) -> 0.32 | D8: =4/12.5 -> 0.32 | E8: =D8 -> 0.32 | F8: 0.32 | G8: 0.32 | H8: 0.32 | I8: 0.32 | J8: 0.32 | K8: 0.32 | L8: 0.32 | M8: 0.32 | N8: 0.32 | O8: 0.32 | P8: 0.32
A9: Total de Fechamentos | B9: =SUM(E9:P9) -> 184.64 | C9: =AVERAGE(D9:P9) -> 14.818462 | D9: =E8*E7 -> 8 | E9: =E8*E7 -> 8 | F9: =F8*F7 -> 9.6 | G9: =G8*G7 -> 10.88 | H9: =H8*H7 -> 12.8 | I9: =I8*I7 -> 14.08 | J9: =J8*J7 -> 16 | K9: =K8*K7 -> 17.28 | L9: =L8*L7 -> 19.2 | ... P9: =P8*P7 -> 19.2
A10: Ticket médio | D10: 7921.7 | E10: =D10 -> 7921.7 | F10: 9000 | G10: 9000 | H10: 10000 | I10: 10000 | J10: 11000 | K10: =J10 -> 11000 | L10: 12000 | M10: =L10 -> 12000 | N10: =M10 -> 12000 | O10: =N10 -> 12000 | P10: =O10 -> 12000
A11: Faturamento Novas vendas | B11: =SUM(E11:P11) -> 2034573.6 | C11: =AVERAGE(E11:P11) -> 169547.8 | D11: =AVERAGE(E10:P10) -> 10660.142 | E11: =E10*E9 -> 63373.6 | F11: =F10*F9 -> 86400 | G11: =G10*G9 -> 97920 | H11: =H10*H9 -> 128000 | I11: =I10*I9 -> 140800 | J11: =J10*J9 -> 176000 | K11: =K10*K9 -> 190080 | L11: =L10*L9 -> 230400 | ... P11: =P10*P9 -> 230400
A12: Acumulado de Negócios | D12: 1 | E12: =E9 -> 8 | F12: =F9+E12 -> 17.6 | G12: =G9+F12 -> 28.48 | H12: =H9+G12 -> 41.28 | I12: =I9+H12 -> 55.36 | J12: =J9+I12 -> 71.36 | K12: =K9+J12 -> 88.64 | L12: =L9+K12 -> 107.84 | M12: =M9+L12 -> 127.04 | ... P12: =P9+O12 -> 184.64
A13: Acumulado de Faturamento | E13: =E11 -> 63373.6 | F13: =F11+E13 -> 149773.6 | G13: =G11+F13 -> 247693.6 | H13: =H11+G13 -> 375693.6 | I13: =I11+H13 -> 516493.6 | J13: =J11+I13 -> 692493.6 | K13: =K11+J13 -> 882573.6 | L13: =L11+K13 -> 1112973.6 | M13: =M11+L13 -> 1343373.6 | ... P13: =P11+O13 -> 2034573.6
A14: Distribuição Faturamento Curva | D14: =AVERAGE(E11:P11) -> 169547.8 | E14: =E4*$D$14 -> 43494.448 | F14: =F4*$D$14 -> 91821.611 | G14: =G4*$D$14 -> 26579.94 | H14: =H4*$D$14 -> 183643.22 | I14: =I4*$D$14 -> 154646.92 | J14: =J4*$D$14 -> 186059.58 | K14: =K4*$D$14 -> 169145.07 | L14: =L4*$D$14 -> 253717.61 | ... P14: =P4*$D$14 -> 217472.24
A15: Margem de Lucro % (custo, comissão, imposto) | C15: 0.4 | D15: 0.62 | E15: =D15 -> 0.62 | F15: =E15 -> 0.62 | G15: =F15 -> 0.62 | H15: =G15 -> 0.62 | I15: =H15 -> 0.62 | J15: =I15 -> 0.62 | K15: =J15 -> 0.62 | L15: =K15 -> 0.62 | ... P15: =O15 -> 0.62 | R15: =900/7000 -> 0.12857143
A16: Lucro Bruto Oper/Serviço | B16: =SUM(E16:P16) -> 1261435.6 | C16: =AVERAGE(E16:P16) -> 105119.64 | D16: =D15*D11 -> 6609.2878 | E16: =E15*E11 -> 39291.632 | F16: =F15*F11 -> 53568 | G16: =G15*G11 -> 60710.4 | H16: =H15*H11 -> 79360 | I16: =I15*I11 -> 87296 | J16: =J15*J11 -> 109120 | K16: =K15*K11 -> 117849.6 | ... P16: =P15*P11 -> 142848
A17: Margens dos Projetos | B17: % | C17: Qtd. Mensal | D17: 1 parcela | E17: =E16/4 -> 9822.908 | F17: =F16/4 -> 13392 | G17: =G16/4 -> 15177.6 | H17: =H16/4 -> 19840 | I17: =I16/4 -> 21824 | J17: =J16/4 -> 27280 | K17: =K16/4 -> 29462.4 | L17: =L16/4 -> 35712 | ... P17: =P16/4 -> 35712
A18: Disponibilidade | B18: =5125/8000 -> 0.640625 | C18: =3*4.28 -> 12.84 | D18: 2 parcela | E18: 0 | F18: =E17 -> 9822.908 | G18: =F17 -> 13392 | H18: =G17 -> 15177.6 | I18: =H17 -> 19840 | J18: =I17 -> 21824 | K18: =J17 -> 27280 | L18: =K17 -> 29462.4 | M18: =L17 -> 35712 | ... P18: =O17 -> 35712
A19: Projeto | B19: =0.55 -> 0.55 | D19: 3 parcela | E19: 0 | G19: =F18 -> 9822.908 | H19: =G18 -> 13392 | I19: =H18 -> 15177.6 | J19: =I18 -> 19840 | K19: =J18 -> 21824 | L19: =K18 -> 27280 | M19: =L18 -> 29462.4 | N19: =M18 -> 35712 | ... P19: =O18 -> 35712
A20: Laudo + G. Risco | B20: =59% -> 0.59 | D20: 4 parcela | E20: 0 | H20: =G19 -> 9822.908 | I20: =H19 -> 13392 | J20: =I19 -> 15177.6 | K20: =J19 -> 19840 | L20: =K19 -> 21824 | M20: =L19 -> 27280 | N20: =M19 -> 29462.4 | O20: =N19 -> 35712 | P20: =O19 -> 35712
D21: Total Lucro Bruto Novo | E21: =SUM(E17:E20) -> 9822.908 | F21: =SUM(F17:F20) -> 23214.908 | G21: =SUM(G17:G20) -> 38392.508 | H21: =SUM(H17:H20) -> 58232.508 | I21: =SUM(I17:I20) -> 70233.6 | J21: =SUM(J17:J20) -> 84121.6 | K21: =SUM(K17:K20) -> 98406.4 | L21: =SUM(L17:L20) -> 114278.4 | ... P21: =SUM(P17:P20) -> 142848
B22: =B24/B11 -> 0.7160732 | D22: Lucro previsto 2025 | E22: 58000 | F22: 39000 | G22: 25000 | H22: 5500
A23: Faturamento XPE | B23: =SUM(E23:P23) -> 2230618.8 | D23: 28000 | E23: =SUM(E21:E22)/E15+$D$23 -> 137391.79 | F23: =SUM(F21:F22)/F15+$D$23 -> 128346.63 | G23: =SUM(G21:G22)/G15+$D$23 -> 130245.98 | H23: =SUM(H21:H22)/H15+$D$23 -> 130794.37 | I23: =SUM(I21:I22)/I15+$D$23 -> 141280 | J23: =SUM(J21:J22)/J15+$D$23 -> 163680 | K23: =SUM(K21:K22)/K15+$D$23 -> 186720 | L23: =SUM(L21:L22)/L15+$D$23 -> 212320 | ... P23: =SUM(P21:P22)/P15+$D$23 -> 258400
A24: Margem de Contribuição Prevista | B24: =SUM(E24:P24) -> 1456903.6 | C24: Receita BRA + outros | D24: =28000*0.84 -> 23520 | E24: =$D$24+E22+E21 -> 91342.908 | F24: =$D$24+F22+F21 -> 85734.908 | G24: =$D$24+G22+G21 -> 86912.508 | H24: =$D$24+H22+H21 -> 87252.508 | I24: =$D$24+I22+I21 -> 93753.6 | J24: =$D$24+J22+J21 -> 107641.6 | K24: =$D$24+K22+K21 -> 121926.4 | L24: =$D$24+L22+L21 -> 137798.4 | ... P24: =$D$24+P22+P21 -> 166368
A25: Custo Fixo Total | B25: ='Premissas gerais'!B99 -> 85921 | E25: =B25 -> 85921 | F25: =E25 -> 85921 | G25: =F25 -> 85921 | H25: =G25 -> 85921 | I25: =H25 -> 85921 | J25: =I25 -> 85921 | K25: =J25 -> 85921 | L25: =K25 -> 85921 | M25: =L25 -> 85921 | ... P25: =O25 -> 85921
A26: Lucro Líquido Mensal | C26: =D27/B23 -> 0.19091188 | D26: =AVERAGE(E26:P26) -> 35487.636 | E26: =E24-E25 -> 5421.908 | F26: =F24-F25 -> -186.092 | G26: =G24-G25 -> 991.508 | H26: =H24-H25 -> 1331.508 | I26: =I24-I25 -> 7832.6 | J26: =J24-J25 -> 21720.6 | K26: =K24-K25 -> 36005.4 | L26: =L24-L25 -> 51877.4 | ... P26: =P24-P25 -> 80447
A27: Lucro Líquido Acumulado | D27: =P27 -> 425851.63 | E27: =E26+C27 -> 5421.908 | F27: =F26+E27 -> 5235.816 | G27: =G26+F27 -> 6227.324 | H27: =H26+G27 -> 7558.832 | I27: =I26+H27 -> 15391.432 | J27: =J26+I27 -> 37112.032 | K27: =K26+J27 -> 73117.432 | L27: =L26+K27 -> 124994.83 | M27: =M26+L27 -> 190760.23 | ... P27: =P26+O27 -> 425851.63
A31: MRR - Plataforma | E31: 0 | F31: 0 | G31: 1
A32: Ticket médio | D32: 100 | E32: =D32 -> 100 | F32: =E32 -> 100 | G32: =F32 -> 100 | H32: =G32 -> 100 | I32: =H32 -> 100 | J32: =I32 -> 100 | K32: =J32 -> 100 | L32: =K32 -> 100 | ... P32: =O32 -> 100
A33: Taxa de conversão | D33: 0.2 | E33: =D33 -> 0.2 | F33: =E33 -> 0.2 | G33: =F33 -> 0.2 | H33: =G33 -> 0.2 | I33: =H33 -> 0.2 | J33: =I33 -> 0.2 | K33: =J33 -> 0.2 | L33: =K33 -> 0.2 | ... P33: =O33 -> 0.2
A34: qtd. Novos clientes | E34: =E33*E9 -> 1.6 | F34: =F33*F9 -> 1.92 | G34: =G33*G9 -> 2.176 | H34: =H33*H9 -> 2.56 | I34: =I33*I9 -> 2.816 | J34: =J33*J9 -> 3.2 | K34: =K33*K9 -> 3.456 | L34: =L33*L9 -> 3.84 | ... P34: =P33*P9 -> 3.84
A35: Acumulado de Clientes | D35: 03 meses sem plataforma | E35: 0 | F35: 0 | G35: 0 | H35: =H34+G35 -> 2.56 | I35: =I34+H35 -> 5.376 | J35: =J34+I35 -> 8.576 | K35: =K34+J35 -> 12.032 | L35: =L34+K35 -> 15.872 | M35: =M34+L35 -> 19.712 | N35: =N34+M35 -> 23.552 | O35: =O34+N35 -> 27.392 | P35: =P34+O35 -> 31.232
A36: Faturamento Mensal | E36: =E35*E32 -> 0 | F36: =F35*F32 -> 0 | G36: =G35*G32 -> 0 | H36: =H35*H32 -> 256 | I36: =I35*I32 -> 537.6 | J36: =J35*J32 -> 857.6 | K36: =K35*K32 -> 1203.2 | L36: =L35*L32 -> 1587.2 | ... P36: =P35*P32 -> 3123.2
A37: Acumulado anual | E37: =E36 -> 0 | F37: =F36+E37 -> 0 | G37: =G36+F37 -> 0 | H37: =H36+G37 -> 256 | I37: =I36+H37 -> 793.6 | J37: =J36+I37 -> 1651.2 | K37: =K36+J37 -> 2854.4 | L37: =L36+K37 -> 4441.6 | M37: =M36+L37 -> 6412.8 | ... P37: =P36+O37 -> 14630.4
A40: MRR - Ger. Carregadores Ticket | D40: 200 | E40: =D40 -> 200 | F40: =E40 -> 200 | G40: =F40 -> 200 | H40: =G40 -> 200 | I40: =H40 -> 200 | J40: =I40 -> 200 | K40: =J40 -> 200 | L40: =K40 -> 200 | ... P40: =O40 -> 200
A41: Taxa de conversão | D41: 0.1 | E41: =D41 -> 0.1 | F41: =E41 -> 0.1 | G41: =F41 -> 0.1 | H41: =G41 -> 0.1 | I41: =H41 -> 0.1 | J41: =I41 -> 0.1 | K41: =J41 -> 0.1 | L41: =K41 -> 0.1 | ... P41: =O41 -> 0.1
A42: qtd. Novos clientes | E42: =E41*E9 -> 0.8 | F42: =F41*F9 -> 0.96 | G42: =G41*G9 -> 1.088 | H42: =H41*H9 -> 1.28 | I42: =I41*I9 -> 1.408 | J42: =J41*J9 -> 1.6 | K42: =K41*K9 -> 1.728 | L42: =L41*L9 -> 1.92 | ... P42: =P41*P9 -> 1.92
A43: Acumulado de Clientes | E43: 0 | F43: 0 | G43: 0 | H43: 0 | I43: 0 | J43: =J42+I43 -> 1.6 | K43: =K42+J43 -> 3.328 | L43: =L42+K43 -> 5.248 | M43: =M42+L43 -> 7.168 | N43: =N42+M43 -> 9.088 | O43: =O42+N43 -> 11.008 | P43: =P42+O43 -> 12.928
A44: Faturamento Mensal | E44: =B43*B40 -> 0 | F44: =C43*C40 -> 0 | G44: =D43*D40 -> 0 | H44: =E43*E40 -> 0 | I44: =F43*F40 -> 0 | J44: =J43*J40 -> 320 | K44: =K43*K40 -> 665.6 | L44: =L43*L40 -> 1049.6 | M44: =M43*M40 -> 1433.6 | N44: =N43*N40 -> 1817.6 | O44: =O43*O40 -> 2201.6 | P44: =P43*P40 -> 2585.6 | Q44: =Q43*Q40 -> 0 | ... S44: =S43*S40 -> 0
A45: Acumulado anual | E45: =E44 -> 0 | F45: =F44 -> 0 | G45: =G44 -> 0 | H45: =H44 -> 0 | I45: =I44+H45 -> 0 | J45: =J44+I45 -> 320 | K45: =K44+J45 -> 985.6 | L45: =L44+K45 -> 2035.2 | M45: =M44+L45 -> 3468.8 | N45: =N44+M45 -> 5286.4 | O45: =O44+N45 -> 7488 | P45: =P44+O45 -> 10073.6 | ... S45: =S44+R45 -> 10073.6
A46: Setup | D46: =3000+3*1500+5000 -> 12500 | J46: =$D$46*J42 -> 20000 | K46: =$D$46*K42 -> 21600 | L46: =$D$46*L42 -> 24000 | M46: =$D$46*M42 -> 24000 | N46: =$D$46*N42 -> 24000 | O46: =$D$46*O42 -> 24000 | P46: =$D$46*P42 -> 24000 | Q46: =$D$46*Q42 -> 0 | ... S46: =$D$46*S42 -> 0
A47: % Setup | D47: 0.5 | E47: =$D47*E46 -> 0 | F47: =$D47*F46 -> 0 | G47: =$D47*G46 -> 0 | H47: =$D47*H46 -> 0 | I47: =$D47*I46 -> 0 | J47: =$D47*J46 -> 10000 | K47: =$D47*K46 -> 10800 | L47: =$D47*L46 -> 12000 | ... S47: =$D47*S46 -> 0
A48: % MRR Hard | D48: 0.7 | E48: =$D48*E44 -> 0 | F48: =$D48*F44 -> 0 | G48: =$D48*G44 -> 0 | H48: =$D48*H44 -> 0 | I48: =$D48*I44 -> 0 | J48: =$D48*J44 -> 224 | K48: =$D48*K44 -> 465.92 | L48: =$D48*L44 -> 734.72 | ... S48: =$D48*S44 -> 0
A49: % MRR Plataforma | D49: 0.75 | E49: =$D49*E36 -> 0 | F49: =$D49*F36 -> 0 | G49: =$D49*G36 -> 0 | H49: =$D49*H36 -> 192 | I49: =$D49*I36 -> 403.2 | J49: =$D49*J36 -> 643.2 | K49: =$D49*K36 -> 902.4 | L49: =$D49*L36 -> 1190.4 | ... S49: =$D49*S36 -> 0
A50: Faturamento Total Plat. + Smart C | C50: =SUM(E50:P50) -> 186304 | D50: =AVERAGE(E50:P50) -> 15525.333 | E50: =E46+E44+E36 -> 0 | F50: =F46+F44+F36 -> 0 | G50: =G46+G44+G36 -> 0 | H50: =H46+H44+H36 -> 256 | I50: =I46+I44+I36 -> 537.6 | J50: =J46+J44+J36 -> 21177.6 | K50: =K46+K44+K36 -> 23468.8 | L50: =L46+L44+L36 -> 26636.8 | ... S50: =S46+S44+S36 -> 0
A51: Margem de Contrib Total tec | C51: =SUM(E51:P51) -> 98824.32 | D51: =AVERAGE(E51:P51) -> 8235.36 | E51: =E49+E48+E47 -> 0 | F51: =F49+F48+F47 -> 0 | G51: =G49+G48+G47 -> 0 | H51: =H49+H48+H47 -> 192 | I51: =I49+I48+I47 -> 403.2 | J51: =J49+J48+J47 -> 10867.2 | K51: =K49+K48+K47 -> 12168.32 | L51: =L49+L48+L47 -> 13925.12 | ... S51: =S49+S48+S47 -> 0
A54: Faturamento Obras
A55: Qtd de Consultorias Mês | B55: Total | C55: Qtd | D55: Taxa
A56: Margem | B56: 110000 | C56: 6 | D56: 0.15
A57: Qtd de Obras Previstas | D57: Ticket | E57: =$D$56*E9 -> 1.2 | F57: =$D$56*F9 -> 1.44 | G57: =$D$56*G9 -> 1.632 | H57: =$D$56*H9 -> 1.92 | I57: =$D$56*I9 -> 2.112 | J57: =$D$56*J9 -> 2.4 | K57: =$D$56*K9 -> 2.592 | L57: =$D$56*L9 -> 2.88 | ... S57: =$D$56*S9 -> 0
A58: Faturamento previsto | B58: Faturamento total | C58: =SUM(E58:P58) -> 507760 | D58: =B56/C56 -> 18333.333 | E58: =E57*$D$58 -> 22000 | F58: =F57*$D$58 -> 26400 | G58: =G57*$D$58 -> 29920 | H58: =H57*$D$58 -> 35200 | I58: =I57*$D$58 -> 38720 | J58: =J57*$D$58 -> 44000 | K58: =K57*$D$58 -> 47520 | L58: =L57*$D$58 -> 52800 | ... S58: =S57*$D$58 -> 0
A59: Parcela 1 | E59: =E58/4 -> 5500 | F59: =F58/4 -> 6600 | G59: =G58/4 -> 7480 | H59: =H58/4 -> 8800 | I59: =I58/4 -> 9680 | J59: =J58/4 -> 11000 | K59: =K58/4 -> 11880 | L59: =L58/4 -> 13200 | ... S59: =S58/4 -> 0
A60: Parcela 2 | F60: =E59 -> 5500 | G60: =F59 -> 6600 | H60: =G59 -> 7480 | I60: =H59 -> 8800 | J60: =I59 -> 9680 | K60: =J59 -> 11000 | L60: =K59 -> 11880 | M60: =L59 -> 13200 | ... S60: =R59 -> 0
A61: Parcela 3 | G61: =F60 -> 5500 | H61: =G60 -> 6600 | I61: =H60 -> 7480 | J61: =I60 -> 8800 | K61: =J60 -> 9680 | L61: =K60 -> 11000 | M61: =L60 -> 11880 | N61: =M60 -> 13200 | ... S61: =R60 -> 0
A62: Parcela 4 | H62: =G61 -> 5500 | I62: =H61 -> 6600 | J62: =I61 -> 7480 | K62: =J61 -> 8800 | L62: =K61 -> 9680 | M62: =L61 -> 11000 | N62: =M61 -> 11880 | O62: =N61 -> 13200 | ... S62: =R61 -> 13200
A63: Total Recebido | E63: =SUM(E59:E62) -> 5500 | F63: =SUM(F59:F62) -> 12100 | G63: =SUM(G59:G62) -> 19580 | H63: =SUM(H59:H62) -> 28380 | I63: =SUM(I59:I62) -> 32560 | J63: =SUM(J59:J62) -> 36960 | K63: =SUM(K59:K62) -> 41360 | L63: =SUM(L59:L62) -> 45760 | ... S63: =SUM(S59:S62) -> 13200
A64: Custo Inicial | D64: 0.45 | E64: =E58*$D$64 -> 9900 | F64: =F58*$D$64 -> 11880 | G64: =G58*$D$64 -> 13464 | H64: =H58*$D$64 -> 15840 | I64: =I58*$D$64 -> 17424 | J64: =J58*$D$64 -> 19800 | K64: =K58*$D$64 -> 21384 | L64: =L58*$D$64 -> 23760 | ... S64: =S58*$D$64 -> 0
A65: Saldo Real (caixa disponivel) | E65: =E63-E64 -> -4400 | F65: =F63-F64 -> 220 | G65: =G63-G64 -> 6116 | H65: =H63-H64 -> 12540 | I65: =I63-I64 -> 15136 | J65: =J63-J64 -> 17160 | K65: =K63-K64 -> 19976 | L65: =L63-L64 -> 22000 | ... S65: =S63-S64 -> 13200
A66: Saldo Acumulado | B66: Receita total | C66: =P66 -> 200068 | E66: =E65 -> -4400 | F66: =F65+E66 -> -4180 | G66: =G65+F66 -> 1936 | H66: =H65+G66 -> 14476 | I66: =I65+H66 -> 29612 | J66: =J65+I66 -> 46772 | K66: =K65+J66 -> 66748 | L66: =L65+K66 -> 88748 | M66: =M65+L66 -> 114268 | ... S66: =S65+R66 -> 279268
A67: Lucro Real | D67: 0.35 | H67: =$D$67*E58 -> 7700 | I67: =$D$67*F58 -> 9240 | J67: =$D$67*G58 -> 10472 | K67: =$D$67*H58 -> 12320 | L67: =$D$67*I58 -> 13552 | M67: =$D$67*J58 -> 15400 | N67: =$D$67*K58 -> 16632 | O67: =$D$67*L58 -> 18480 | ... S67: =$D$67*P58 -> 18480
A68: Margem Contribuição Obras | D68: 0.35 | E68: =E58*$D$68 -> 7700 | F68: =F58*$D$68 -> 9240 | G68: =G58*$D$68 -> 10472 | H68: =H58*$D$68 -> 12320 | I68: =I58*$D$68 -> 13552 | J68: =J58*$D$68 -> 15400 | K68: =K58*$D$68 -> 16632 | L68: =L58*$D$68 -> 18480 | ... S68: =S58*$D$68 -> 0
A70: Faturamento Total Global | B70: =SUM(E70:P70) -> 3432442.8 | C70: média | D70: =AVERAGE(E70:P70) -> 286036.9 | E70: =E58+E76 -> 181391.79 | F70: =F58+F76 -> 181146.63 | G70: =G58+G76 -> 190085.98 | H70: =H58+H76 -> 201450.37 | I70: =I58+I76 -> 219257.6 | J70: =J58+J76 -> 272857.6 | K70: =K58+K76 -> 305228.8 | L70: =L58+L76 -> 344556.8 | ... P70: =P58+P76 -> 393708.8
C75: Total | D75: Média
A76: Fatutamento XPE Global | C76: =SUM(E76:P76) -> 2924682.8 | D76: =AVERAGE(E76:P76) -> 243723.56 | E76: =E50+E58+E23 -> 159391.79 | F76: =F50+F58+F23 -> 154746.63 | G76: =G50+G58+G23 -> 160165.98 | H76: =H50+H58+H23 -> 166250.37 | I76: =I50+I58+I23 -> 180537.6 | J76: =J50+J58+J23 -> 228857.6 | K76: =K50+K58+K23 -> 257708.8 | L76: =L50+L58+L23 -> 291756.8 | ... P76: =P50+P58+P23 -> 340908.8
A77: Margem LL XPE Global | B77: =C77/C76 -> 0.22120415 | C77: =SUM(E77:P77) -> 646951.95 | D77: =AVERAGE(E77:P77) -> 53912.663 | E77: =E67+E51+E24-E25 -> 5421.908 | F77: =F67+F51+F24-F25 -> -186.092 | G77: =G67+G51+G24-G25 -> 991.508 | H77: =H67+H51+H24-H25 -> 9223.508 | I77: =I67+I51+I24-I25 -> 17475.8 | J77: =J67+J51+J24-J25 -> 43059.8 | K77: =K67+K51+K24-K25 -> 60493.72 | L77: =L67+L51+L24-L25 -> 79354.52 | ... P77: =P67+P51+P24-P25 -> 115079.32
A81: Contador de Síndicos | C81: =SUM(E81:P81) -> 115.4 | D81: =5/E9 -> 0.625 | E81: =$D$81*E9 -> 5 | F81: =$D$81*F9 -> 6 | G81: =$D$81*G9 -> 6.8 | H81: =$D$81*H9 -> 8 | I81: =$D$81*I9 -> 8.8 | J81: =$D$81*J9 -> 10 | K81: =$D$81*K9 -> 10.8 | L81: =$D$81*L9 -> 12 | ... P81: =$D$81*P9 -> 12
A82: Orçamento Máquina Indicações e Rel. | D82: 0.025 | E82: =$D$82*E76 -> 3984.7947 | F82: =$D$82*F76 -> 3868.6656 | G82: =$D$82*G76 -> 4004.1495 | H82: =$D$82*H76 -> 4156.2592 | I82: =$D$82*I76 -> 4513.44 | J82: =$D$82*J76 -> 5721.44 | K82: =$D$82*K76 -> 6442.72 | L82: =$D$82*L76 -> 7293.92 | ... P82: =$D$82*P76 -> 8522.72
C83: Fesindico | D83: =SUM(E83:P83) -> 6000 | E83: 600 | F83: =E83 -> 600 | G83: =F83 -> 600 | H83: =G83 -> 600 | I83: =H83 -> 600 | J83: =I83 -> 600 | K83: =J83 -> 600 | L83: =K83 -> 600 | M83: =L83 -> 600 | N83: =M83 -> 600

Sheet Reformas
A1: Investimentos Infraestrutura
A3: Climatização das duas salas
A4: Ar-condicionado 24.000 btu
A5: Cobertura das paredes com acabamento
A6: Outros custos da sala
A8: Expansão e reorganização das estações de trabalho
A9: Levantar necessidades de cadeiras e mesas e extensões
A13: Almoxarifado/organização de materiais de serviços
A14: fazer orçamento do que precisa para ficar tudo organizado e gerível visualmente.
A18: Sala de Refeição e Recepção
A19: Cobertura + detalhes verde + móvel e adesivos
A20: microondas
... A33: Melhorar condições de trabalho individual
A34: Jonildo | B34: Monitor
A35: Paulo Araújo | B35: Monitor
A36: Kalebe | B36: Monitor
A40: Lista de compras e materiais empresa com local definido e responsável por comprar e manter
A47: Área externa - Pracinha é Nossa
A48: -
A49: -
A50: -
A52: Faxina da casa rita toda semana

Sheet Única coisa
A1: Objetivos
A2: Aumentar Ticket +20%
A3: Aumentar ticket 12k
A4: Reduzir custo Oper. -40%
A5: Atender ponta-a-ponta a jornada da Eletromobilidade | B5: Melhorar posicionamento -> Percepção de Valor
A6: MRR Digital + Hard.
A7: Máquina de Indicações e Relacionamento
A9: Serviços de CS
A10: Eletrocalha
A11: Melhorias CDM
A12: Inspeções
A13: Implantação Sist. Carregadores
A14: Botão de Emergência
A16: Plataforma de Gestão de Energia p/ Condomínios
A17: Sistemas e Automações de Processos Internos
A18: Ferramenta Mobile Offline First
A19: Gestão Clickup
... A25: Metas de Novas Receitas -> Plataforma + Hardware + Setup
A26: Setup + obras | B26: Fat. Mensal | C26: 100k
B27: MRR | C27: 10k

Sheet Cronograma PE XPE
A1: Objetivos Principais | D1: Segunda | E1: Terça | F1: Quarta | G1: Quinta | H1: Sexta | J1: Segunda (22)
C2: Manhã | D2: Alinhamento Meta Global 2026. Revisão dos Numeros e Projeção mensal. Considerar calendário, Copa do mundo 26, Eleição, Festividades e Crescimento limitado a geração de Leads. | E2: Fazer o obvio e fácil primeiro. Detalhamento dos resultados mensais comerciais, os objetivos de geração de lead e prever as demandas de projeto. Saber o que será exigido de time e de infraestrutura. Pessoas, material, etc.. Tudo obvio e incluir na projeção com os marcos. O que será feito e quem faz o que? (acho interessante aqui considerar no planejamento exatamente o que temos hoje e o time tech vai justamente viabilizar o resto acontecer. Planejamento financeiro mkt relacionamento, indicações, eventos, salários, melhorias no local, etc... | F2: Terminar o mais importante | G2: Desdobramento Coletivo das Metas | H2: Apresentação do planejamento por área com desdobramento de responsabilidade.
C3: Tarde | D3: Levantamento dos principais desdobramentos estratégicos para alcançar a meta. Alguns: Estratégia de Indicação, Marketing de Relacionamento, Máquina de Indicações. Escalar o operacional com tecnologia (mapear projetos cruciais - App interno, plataforma para clientes, produto específico ger. carregadores, etc...) O que n podemos esquecer: O que precisamos manter? | E3: Fazer o não obvio e mais difícil. Planejamento do crescimento da receita recorrente com novos produtos. Planejamento da parte de obras. Gestão de Pessoas. Novo posicionamento Mídias sociais, rotinas e resultados esperados... | F3: Planejar qual história queremos contar em tudo que fazemos. A missão, o porquê para aumentar o valor percebido em tudo que fazemos e dá direcionamento. "A melhor apresentação" com a melhor intenção e promessa! | G3: Desdobramento Coletivo das Metas | H3: Apresentação do planejamento por área com desdobramento de responsabilidade.
C4: Noite
D5: Não esquecer da única coisa global | E5: Única coisa por área
D8: Lembretes:
D9: Reorganização da Sala - Orçamentos de infraestrutura (climatização, pintura, sala de estar, sala de reunião, copa, etc... Materiais individuais)
D10: Tudo que precisa ser comprado de básico
D11: Quais rotinas de manutenção da ordem? Quais responsabilidades? Limpeza e Condições de Trabalho
D12: Rotina geral da empresa. Primeiro o mais importante: 1ª Segunda-feira do mês: 08h -> Revisão do planejamento estratégico do mês. Planejamento resumido a 1 página com ritos, rotinas, objetivos e responsabilidades
D13: Reunião semanal de abertura e fechamento de semana + PDCA.
D14: Reconhecimentos Mensais, públicos
D15: Reunião de Diretoria invocada sempre que algo está fora do planejamento. Prestar contas, como pedir ajuda e resolver (mínima 30 dias). Não atrapalhar o comercial.

Sheet Sala material
A1: Reforma da sala | B1: Preço | C1: m² | D1: Projeto m² | E1: Qtd peças | F1: Arredondar | G1: Total
A2: Bloco branco diam | B2: 77.81 | C2: =100*0.25*0.25 -> 6.25 | D2: =2.15*(1.15+1.8) -> 6.3425 | E2: =D2/C2 -> 1.0148 | F2: 1 | G2: =F2*B2 -> 77.81 | J2: Estante Led | K2: 6 | L2: 2 | N2: =L2*K2 -> 12
A3: Bloco preto tijolo | B3: =55 -> 55 | C3: =10*0.7*0.77 -> 5.39 | D3: 6.5 | E3: =D3/C3 -> 1.2059369 | F3: 2 | G3: =F3*B3 -> 110 | K3: 2 | L3: 2 | M3: 2 | N3: =SUM(K3:M3) -> 6
A4: Isopor | B4: 100 | C4: =0.5*1 -> 0.5 | D4: 30 | E4: =D4/C4 -> 60 | F4: 60 | G4: =F4*B4 -> 6000 | K4: =2.15*2+5.4 -> 9.7 | L4: =2.15+2.15+2.15+3 -> 9.45 | N4: =L4+K4 -> 19.15
A5: Bloco preto diam | B5: 77.81 | C5: =100*0.25*0.25 -> 6.25 | D5: =2.15*(5.4) -> 11.61 | E5: =D5/C5 -> 1.8576 | F5: 2 | G5: =F5*B5 -> 155.62 | N5: =N4+N3+N2 -> 37.15
A6: Telha zinco | B6: 180 | C6: =3.05*1.1 -> 3.355 | D6: =3.05*2 -> 6.1 | E6: =D6/C6 -> 1.8181818 | F6: 2 | G6: =F6*B6 -> 360
A7: Parede verde | B7: 500 | C7: =25*0.4*0.6 -> 6 | D7: =6*0.6 -> 3.6 | E7: =D7/C7 -> 0.6 | F7: 1 | G7: =F7*B7 -> 500
A8: Estantes | B8: 200 | C8: 1 | D8: 2 | E8: =D8/C8 -> 2 | F8: =E8 -> 2 | G8: =F8*B8 -> 400
A9: Fita led verde | B9: 200 | C9: 1 | D9: 1 | E9: =D9/C9 -> 1 | F9: =E9 -> 1 | G9: =F9*B9 -> 200 | I9: =60*6.4 -> 384
A10: Spot luz 4x | B10: 50 | C10: 2 | D10: 10 | E10: =D10/C10 -> 5 | F10: 5 | G10: =F10*B10 -> 250
A11: Grade preta | B11: 66.9 | C11: =0.3*0.4*10 -> 1.2 | D11: =2.15*(5.4/3) -> 3.87 | E11: =D11/C11 -> 3.225 | F11: 4 | G11: =F11*B11 -> 267.6 | J11: =5.4/3 -> 1.8 | L11: =6*2.8 -> 16.8 | M11: =L11/5.39 -> 3.1168831 | N11: 4*55
A12: Logo 1,20 | B12: 350 | C12: 1 | D12: 1 | E12: =D12/C12 -> 1 | F12: 1 | G12: =F12*B12 -> 350
G13: =SUM(G2:G12) -> 8671.03
B16: 2.1 | C16: 5.12 | D16: =C16*B16 -> 10.752
B17: 2.1 | C17: 5.72 | D17: =C17*B17 -> 12.012
B18: 2.1 | C18: 3.13 | D18: =C18*B18 -> 6.573
D19: =SUM(D16:D18) -> 29.337

Sheet Fernando
A1: Fernando
A2: 1. Aumentar nosso ticket médio -> Melhorar nossa apresentação + Storytelling + Diferenciação e Percepção de valor + ritos e rotinas | B2: primeiro quarter acompanhar e montar junto com comercial | L2: 0.2
A3: 2. Design Plataforma Digital para gestão elétrica condominial totalmente alinhada a Percepção de valor (Vender o que eles querem e entregar o que eles precisam) | B3: Fazer o design da primeira versão da plataforma web
A4: 3. Design Produto e Serviço de Gerenciamento de Carga condominial (Integração com a plataforma + Gestão de carregadores)
A5: 4. Plano Global para tornar tudo isso em recorrência com um combo completo, rotinas periódicas e estratégias Hooked.
A6: 5. Aumentar o lucro operacional completo (Visão de escala operacional com tecnologia e automação de processos) | L6: 0.2
A7: 6. Suporte para melhorar nosso sistema de indica
A10: Audrey
A11: Calendário 2026 com foco em aumentar as vendas através de relacionamento. Considerar eventos importantes
A12: Estratégias de relacionamento para gerar indicações
A13: Parcerias estratégicas (quem conhecemos, devemos conhecer, quem precisa nos conhecer, lembrando)
A14: Direcionamento do conteúdo e materiais para isso acontecer.

Sheet Projeção Biel
A1: Faturamento Consultoria
A2: Mês | B2: Total | C2: Média | D2: Referência | E2: 1 | F2: 2 | G2: 3 | H2: 4 | I2: 5 | J2: 6 | K2: 7 | L2: 8 | M2: 9 | N2: 10 | O2: 11 | P2: 12
A3: Curva Faturamento R$ | B3: =SUM(E3:P3) -> 2008800 | C3: =AVERAGE(E3:P3) -> 167400 | E3: ='Premissas gerais'!O5 -> 42943.468 | F3: ='Premissas gerais'!P5 -> 90658.432 | G3: ='Premissas gerais'!Q5 -> 26243.23 | H3: ='Premissas gerais'!R5 -> 181316.86 | I3: ='Premissas gerais'!S5 -> 152687.89 | J3: ='Premissas gerais'!T5 -> 183702.61 | K3: ='Premissas gerais'!U5 -> 167002.38 | L3: ='Premissas gerais'!V5 -> 250503.56 | ... P3: ='Premissas gerais'!Z5 -> 214717.34
A4: Curva Faturamento % | B4: 1 | C4: =AVERAGE(E4:P4) -> 1 | E4: =E3/$C$3 -> 0.25653207 | F4: =F3/$C$3 -> 0.5415677 | G4: =G3/$C$3 -> 0.1567696 | H4: =H3/$C$3 -> 1.0831354 | I4: =I3/$C$3 -> 0.91211401 | J4: =J3/$C$3 -> 1.0973872 | K4: =K3/$C$3 -> 0.9976247 | L4: =L3/$C$3 -> 1.4964371 | ... P4: =P3/$C$3 -> 1.2826603
A5: Qtd Vendedores | B5: =C5 -> 2 | C5: =AVERAGE(E5:P5) -> 2 | D5: 2 | E5: =D5 -> 2 | F5: =E5 -> 2 | G5: =F5 -> 2 | H5: =G5 -> 2 | I5: =H5 -> 2 | J5: =I5 -> 2 | K5: 2 | L5: =K5 -> 2 | M5: =L5 -> 2 | N5: =M5 -> 2 | O5: =N5 -> 2 | P5: =O5 -> 2
A6: Funil de Vendas Atual | B6: 84 | E6: 84
A7: Topo de Funil (Indicações/oportunidades) | B7: =SUM(E7:P7) -> 907.5 | E7: =E8*3 -> 37.5 | F7: =F8*3 -> 45 | G7: =G8*3 -> 60 | H7: =H8*3 -> 66 | I7: =I8*3 -> 72 | J7: =J8*3 -> 78 | K7: =K8*3 -> 84 | L7: =L8*3 -> 90 | ... P7: =P8*3 -> 90
A8: Qtd Visita / Vendedor | B8: =SUM(E8:P8) -> 302.5 | C8: =AVERAGE(E8:P8) -> 25.208333 | D8: 12.5 | E8: =D8 -> 12.5 | F8: 15 | G8: 20 | H8: 22 | I8: 24 | J8: 26 | K8: 28 | L8: 30 | M8: 32 | N8: 33 | O8: 30 | P8: 30
A9: Total de Propostas | B9: =SUM(E9:P9) -> 605 | C9: =AVERAGE(E9:P9) -> 50.416667 | D9: =E8*E5 -> 25 | E9: =E5*E8 -> 25 | F9: =F5*F8 -> 30 | G9: =G5*G8 -> 40 | H9: =H5*H8 -> 44 | I9: =I5*I8 -> 48 | J9: =J5*J8 -> 52 | K9: =K5*K8 -> 56 | L9: =L5*L8 -> 60 | ... P9: =P5*P8 -> 60
A10: Taxa de Conversa Prop/Fech | B10: =SUM(E10:P10) -> 3.84 | C10: =AVERAGE(E10:P10) -> 0.32 | D10: 3.32 | E10: 0.32 | F10: 0.32 | G10: 0.32 | H10: 0.32 | I10: 0.32 | J10: 0.32 | K10: 0.32 | L10: 0.32 | M10: 0.32 | N10: 0.32 | O10: 0.32 | P10: 0.32
A11: Total de Fechamentos | B11: =SUM(E11:P11) -> 193.6 | C11: =AVERAGE(D11:P11) -> 15.507692 | D11: =E10*E9 -> 8 | E11: =E10*E9 -> 8 | F11: =F10*F9 -> 9.6 | G11: =G10*G9 -> 12.8 | H11: =H10*H9 -> 14.08 | I11: =I10*I9 -> 15.36 | J11: =J10*J9 -> 16.64 | K11: =K10*K9 -> 17.92 | L11: =L10*L9 -> 19.2 | ... P11: =P10*P9 -> 19.2
A12: Ticket médio | D12: 7921.7 | E12: =D12 -> 7921.7 | F12: 9000 | G12: 9000 | H12: 10000 | I12: 10000 | J12: 11000 | K12: =J12 -> 11000 | L12: 12000 | M12: =L12 -> 12000 | N12: =M12 -> 12000 | O12: =N12 -> 12000 | P12: =O12 -> 12000
A13: Faturamento Novas vendas | B13: =SUM(E13:P13) -> 2129933.6 | C13: =AVERAGE(E13:P13) -> 177494.47 | D13: =AVERAGE(E12:P12) -> 10660.142 | E13: =E12*E11 -> 63373.6 | F13: =F12*F11 -> 86400 | G13: =G12*G11 -> 115200 | H13: =H12*H11 -> 140800 | I13: =I12*I11 -> 153600 | J13: =J12*J11 -> 183040 | K13: =K12*K11 -> 197120 | L13: =L12*L11 -> 230400 | ... P13: =P12*P11 -> 230400
A14: Acumulado de Negócios | D14: 1 | E14: =E11 -> 8 | F14: =F11+E14 -> 17.6 | G14: =G11+F14 -> 30.4 | H14: =H11+G14 -> 44.48 | I14: =I11+H14 -> 59.84 | J14: =J11+I14 -> 76.48 | K14: =K11+J14 -> 94.4 | L14: =L11+K14 -> 113.6 | M14: =M11+L14 -> 134.08 | ... P14: =P11+O14 -> 193.6
A15: Acumulado de Faturamento | E15: =E13 -> 63373.6 | F15: =F13+E15 -> 149773.6 | G15: =G13+F15 -> 264973.6 | H15: =H13+G15 -> 405773.6 | I15: =I13+H15 -> 559373.6 | J15: =J13+I15 -> 742413.6 | K15: =K13+J15 -> 939533.6 | L15: =L13+K15 -> 1169933.6 | M15: =M13+L15 -> 1415693.6 | ... P15: =P13+O15 -> 2129933.6
A16: Distribuição Faturamento Curva | D16: =AVERAGE(E13:P13) -> 177494.47 | E16: =E4*$D$16 -> 45533.022 | F16: =F4*$D$16 -> 96125.269 | G16: =G4*$D$16 -> 27825.736 | H16: =H4*$D$16 -> 192250.54 | I16: =I4*$D$16 -> 161895.19 | J16: =J4*$D$16 -> 194780.15 | K16: =K4*$D$16 -> 177072.86 | L16: =L4*$D$16 -> 265609.3 | ... P16: =P4*$D$16 -> 227665.11
A17: Margem de Lucro % (custo, comissão, imposto) | C17: 0.4 | D17: 0.62 | E17: =D17 -> 0.62 | F17: =E17 -> 0.62 | G17: =F17 -> 0.62 | H17: =G17 -> 0.62 | I17: =H17 -> 0.62 | J17: =I17 -> 0.62 | K17: =J17 -> 0.62 | L17: =K17 -> 0.62 | ... P17: =O17 -> 0.62 | R17: =900/7000 -> 0.12857143
A18: Lucro Bruto Oper/Serviço | B18: =SUM(E18:P18) -> 1320558.8 | C18: =AVERAGE(E18:P18) -> 110046.57 | D18: =D17*D13 -> 6609.2878 | E18: =E17*E13 -> 39291.632 | F18: =F17*F13 -> 53568 | G18: =G17*G13 -> 71424 | H18: =H17*H13 -> 87296 | I18: =I17*I13 -> 95232 | J18: =J17*J13 -> 113484.8 | K18: =K17*K13 -> 122214.4 | ... P18: =P17*P13 -> 142848
A19: Margens dos Projetos | B19: % | C19: Qtd. Mensal | D19: 1 parcela | E19: =E18/4 -> 9822.908 | F19: =F18/4 -> 13392 | G19: =G18/4 -> 17856 | H19: =H18/4 -> 21824 | I19: =I18/4 -> 23808 | J19: =J18/4 -> 28371.2 | K19: =K18/4 -> 30553.6 | L19: =L18/4 -> 35712 | ... P19: =P18/4 -> 35712
A20: Disponibilidade | B20: =5125/8000 -> 0.640625 | C20: =3*4.28 -> 12.84 | D20: 2 parcela | E20: 0 | F20: =E19 -> 9822.908 | G20: =F19 -> 13392 | H20: =G19 -> 17856 | I20: =H19 -> 21824 | J20: =I19 -> 23808 | K20: =J19 -> 28371.2 | L20: =K19 -> 30553.6 | M20: =L19 -> 35712 | ... P20: =O19 -> 35712
A21: Projeto | B21: =0.55 -> 0.55 | D21: 3 parcela | E21: 0 | G21: =F20 -> 9822.908 | H21: =G20 -> 13392 | I21: =H20 -> 17856 | J21: =I20 -> 21824 | K21: =J20 -> 23808 | L21: =K20 -> 28371.2 | M21: =L20 -> 30553.6 | N21: =M20 -> 35712 | ... P21: =O20 -> 39283.2
A22: Laudo + G. Risco | B22: =59% -> 0.59 | D22: 4 parcela | E22: 0 | H22: =G21 -> 9822.908 | I22: =H21 -> 13392 | J22: =I21 -> 17856 | K22: =J21 -> 21824 | L22: =K21 -> 23808 | M22: =L21 -> 28371.2 | N22: =M21 -> 30553.6 | O22: =N21 -> 35712 | P22: =O21 -> 38092.8
D23: Total Lucro Bruto Novo | E23: =SUM(E19:E22) -> 9822.908 | F23: =SUM(F19:F22) -> 23214.908 | G23: =SUM(G19:G22) -> 41070.908 | H23: =SUM(H19:H22) -> 62894.908 | I23: =SUM(I19:I22) -> 76880 | J23: =SUM(J19:J22) -> 91859.2 | K23: =SUM(K19:K22) -> 104556.8 | L23: =SUM(L19:L22) -> 118444.8 | ... P23: =SUM(P19:P22) -> 148800
B24: =B26/B13 -> 0.7100952 | D24: Lucro previsto 2025 | E24: 58000 | F24: 39000 | G24: 25000 | H24: 5500
A25: Faturamento XPE | B25: =SUM(E25:P25) -> 2320218.8 | D25: 28000 | E25: =SUM(E23:E24)/E17+$D$25 -> 137391.79 | F25: =SUM(F23:F24)/F17+$D$25 -> 128346.63 | G25: =SUM(G23:G24)/G17+$D$25 -> 134565.98 | H25: =SUM(H23:H24)/H17+$D$25 -> 138314.37 | I25: =SUM(I23:I24)/I17+$D$25 -> 152000 | J25: =SUM(J23:J24)/J17+$D$25 -> 176160 | K25: =SUM(K23:K24)/K17+$D$25 -> 196640 | L25: =SUM(L23:L24)/L17+$D$25 -> 219040 | ... P25: =SUM(P23:P24)/P17+$D$25 -> 268000
A26: Margem de Contribuição Prevista | B26: =SUM(E26:P26) -> 1512455.6 | C26: Receita BRA + outros | D26: =28000*0.84 -> 23520 | E26: =$D$26+E24+E23 -> 91342.908 | F26: =$D$26+F24+F23 -> 85734.908 | G26: =$D$26+G24+G23 -> 89590.908 | H26: =$D$26+H24+H23 -> 91914.908 | I26: =$D$26+I24+I23 -> 100400 | J26: =$D$26+J24+J23 -> 115379.2 | K26: =$D$26+K24+K23 -> 128076.8 | L26: =$D$26+L24+L23 -> 141964.8 | ... P26: =$D$26+P24+P23 -> 172320
A27: Custo Fixo Total | B27: ='Premissas gerais'!B99 -> 85921 | E27: =B27 -> 85921 | F27: =E27 -> 85921 | G27: =F27 -> 85921 | H27: =G27 -> 85921 | I27: =H27 -> 85921 | J27: =I27 -> 85921 | K27: =J27 -> 85921 | L27: =K27 -> 85921 | M27: =L27 -> 85921 | ... P27: =O27 -> 85921
A28: Lucro Líquido Mensal | C28: =D29/B25 -> 0.207482 | D28: =AVERAGE(E28:P28) -> 40116.969 | E28: =E26-E27 -> 5421.908 | F28: =F26-F27 -> -186.092 | G28: =G26-G27 -> 3669.908 | H28: =H26-H27 -> 5993.908 | I28: =I26-I27 -> 14479 | J28: =J26-J27 -> 29458.2 | K28: =K26-K27 -> 42155.8 | L28: =L26-L27 -> 56043.8 | ... P28: =P26-P27 -> 86399
A29: Lucro Líquido Acumulado | D29: =P29 -> 481403.63 | E29: =E28+C29 -> 5421.908 | F29: =F28+E29 -> 5235.816 | G29: =G28+F29 -> 8905.724 | H29: =H28+G29 -> 14899.632 | I29: =I28+H29 -> 29378.632 | J29: =J28+I29 -> 58836.832 | K29: =K28+J29 -> 100992.63 | L29: =L28+K29 -> 157036.43 | M29: =M28+L29 -> 227365.03 | ... P29: =P28+O29 -> 481403.63
A33: MRR - Plataforma | E33: 0 | F33: 0 | G33: 1
A34: Ticket médio | D34: 100 | E34: =D34 -> 100 | F34: =E34 -> 100 | G34: =F34 -> 100 | H34: =G34 -> 100 | I34: =H34 -> 100 | J34: =I34 -> 100 | K34: =J34 -> 100 | L34: =K34 -> 100 | ... P34: =O34 -> 100
A35: Taxa de conversão | D35: 0.2 | E35: =D35 -> 0.2 | F35: =E35 -> 0.2 | G35: =F35 -> 0.2 | H35: =G35 -> 0.2 | I35: =H35 -> 0.2 | J35: =I35 -> 0.2 | K35: =J35 -> 0.2 | L35: =K35 -> 0.2 | ... P35: =O35 -> 0.2
A36: qtd. Novos clientes | E36: =E35*E11 -> 1.6 | F36: =F35*F11 -> 1.92 | G36: =G35*G11 -> 2.56 | H36: =H35*H11 -> 2.816 | I36: =I35*I11 -> 3.072 | J36: =J35*J11 -> 3.328 | K36: =K35*K11 -> 3.584 | L36: =L35*L11 -> 3.84 | ... P36: =P35*P11 -> 3.84
A37: Acumulado de Clientes | D37: 03 meses sem plataforma | E37: 0 | F37: 0 | G37: 0 | H37: =H36+G37 -> 2.816 | I37: =I36+H37 -> 5.888 | J37: =J36+I37 -> 9.216 | K37: =K36+J37 -> 12.8 | L37: =L36+K37 -> 16.64 | M37: =M36+L37 -> 20.736 | N37: =N36+M37 -> 24.96 | O37: =O36+N37 -> 28.8 | P37: =P36+O37 -> 32.64
A38: Faturamento Mensal | E38: =E37*E34 -> 0 | F38: =F37*F34 -> 0 | G38: =G37*G34 -> 0 | H38: =H37*H34 -> 281.6 | I38: =I37*I34 -> 588.8 | J38: =J37*J34 -> 921.6 | K38: =K37*K34 -> 1280 | L38: =L37*L34 -> 1664 | ... P38: =P37*P34 -> 3264
A39: Acumulado anual | E39: =E38 -> 0 | F39: =F38+E39 -> 0 | G39: =G38+F39 -> 0 | H39: =H38+G39 -> 281.6 | I39: =I38+H39 -> 870.4 | J39: =J38+I39 -> 1792 | K39: =K38+J39 -> 3072 | L39: =L38+K39 -> 4736 | M39: =M38+L39 -> 6809.6 | ... P39: =P38+O39 -> 15449.6
A42: MRR - Ger. Carregadores Ticket | D42: 200 | E42: =D42 -> 200 | F42: =E42 -> 200 | G42: =F42 -> 200 | H42: =G42 -> 200 | I42: =H42 -> 200 | J42: =I42 -> 200 | K42: =J42 -> 200 | L42: =K42 -> 200 | ... P42: =O42 -> 200
A43: Taxa de conversão | D43: 0.1 | E43: =D43 -> 0.1 | F43: =E43 -> 0.1 | G43: =F43 -> 0.1 | H43: =G43 -> 0.1 | I43: =H43 -> 0.1 | J43: =I43 -> 0.1 | K43: =J43 -> 0.1 | L43: =K43 -> 0.1 | ... P43: =O43 -> 0.1
A44: qtd. Novos clientes | E44: =E43*E11 -> 0.8 | F44: =F43*F11 -> 0.96 | G44: =G43*G11 -> 1.28 | H44: =H43*H11 -> 1.408 | I44: =I43*I11 -> 1.536 | J44: =J43*J11 -> 1.664 | K44: =K43*K11 -> 1.792 | L44: =L43*L11 -> 1.92 | ... P44: =P43*P11 -> 1.92
A45: Acumulado de Clientes | E45: 0 | F45: 0 | G45: 0 | H45: 0 | I45: 0 | J45: =J44+I45 -> 1.664 | K45: =K44+J45 -> 3.456 | L45: =L44+K45 -> 5.376 | M45: =M44+L45 -> 7.424 | N45: =N44+M45 -> 9.536 | O45: =O44+N45 -> 11.456 | P45: =P44+O45 -> 13.376
A46: Faturamento Mensal | E46: =B45*B42 -> 0 | F46: =C45*C42 -> 0 | G46: =D45*D42 -> 0 | H46: =E45*E42 -> 0 | I46: =F45*F42 -> 0 | J46: =J45*J42 -> 332.8 | K46: =K45*K42 -> 691.2 | L46: =L45*L42 -> 1075.2 | M46: =M45*M42 -> 1484.8 | N46: =N45*N42 -> 1907.2 | O46: =O45*O42 -> 2291.2 | P46: =P45*P42 -> 2675.2 | Q46: =Q45*Q42 -> 0 | ... S46: =S45*S42 -> 0
A47: Acumulado anual | E47: =E46 -> 0 | F47: =F46 -> 0 | G47: =G46 -> 0 | H47: =H46 -> 0 | I47: =I46+H47 -> 0 | J47: =J46+I47 -> 332.8 | K47: =K46+J47 -> 1024 | L47: =L46+K47 -> 2099.2 | M47: =M46+L47 -> 3584 | N47: =N46+M47 -> 5491.2 | O47: =O46+N47 -> 7782.4 | P47: =P46+O47 -> 10457.6 | ... S47: =S46+R47 -> 10457.6
A48: Setup | D48: =3000+3*1500+5000 -> 12500 | J48: =$D$48*J44 -> 20800 | K48: =$D$48*K44 -> 22400 | L48: =$D$48*L44 -> 24000 | M48: =$D$48*M44 -> 25600 | N48: =$D$48*N44 -> 26400 | O48: =$D$48*O44 -> 24000 | P48: =$D$48*P44 -> 24000 | Q48: =$D$48*Q44 -> 0 | ... S48: =$D$48*S44 -> 0
A49: % Setup | D49: 0.5 | E49: =$D49*E48 -> 0 | F49: =$D49*F48 -> 0 | G49: =$D49*G48 -> 0 | H49: =$D49*H48 -> 0 | I49: =$D49*I48 -> 0 | J49: =$D49*J48 -> 10400 | K49: =$D49*K48 -> 11200 | L49: =$D49*L48 -> 12000 | ... S49: =$D49*S48 -> 0
A50: % MRR Hard | D50: 0.7 | E50: =$D50*E46 -> 0 | F50: =$D50*F46 -> 0 | G50: =$D50*G46 -> 0 | H50: =$D50*H46 -> 0 | I50: =$D50*I46 -> 0 | J50: =$D50*J46 -> 232.96 | K50: =$D50*K46 -> 483.84 | L50: =$D50*L46 -> 752.64 | ... S50: =$D50*S46 -> 0
A51: % MRR Plataforma | D51: 0.75 | E51: =$D51*E38 -> 0 | F51: =$D51*F38 -> 0 | G51: =$D51*G38 -> 0 | H51: =$D51*H38 -> 211.2 | I51: =$D51*I38 -> 441.6 | J51: =$D51*J38 -> 691.2 | K51: =$D51*K38 -> 960 | L51: =$D51*L38 -> 1248 | ... S51: =$D51*S38 -> 0
A52: Faturamento Total Plat. + Smart C | C52: =SUM(E52:P52) -> 193107.2 | D52: =AVERAGE(E52:P52) -> 16092.267 | E52: =E48+E46+E38 -> 0 | F52: =F48+F46+F38 -> 0 | G52: =G48+G46+G38 -> 0 | H52: =H48+H46+H38 -> 281.6 | I52: =I48+I46+I38 -> 588.8 | J52: =J48+J46+J38 -> 22054.4 | K52: =K48+K46+K38 -> 24371.2 | L52: =L48+L46+L38 -> 26739.2 | ... S52: =S48+S46+S38 -> 0
A53: Margem de Contrib Total tec | C53: =SUM(E53:P53) -> 102507.52 | D53: =AVERAGE(E53:P53) -> 8542.2933 | E53: =E51+E50+E49 -> 0 | F53: =F51+F50+F49 -> 0 | G53: =G51+G50+G49 -> 0 | H53: =H51+H50+H49 -> 211.2 | I53: =I51+I50+I49 -> 441.6 | J53: =J51+J50+J49 -> 11324.16 | K53: =K51+K50+K49 -> 12643.84 | L53: =L51+L50+L49 -> 14000.64 | ... S53: =S51+S50+S49 -> 0
A56: Faturamento Obras
A57: Qtd de Consultorias Mês | B57: Total | C57: Qtd | D57: Taxa
A58: Margem | B58: 110000 | C58: 6 | D58: 0.13
A59: Qtd de Obras Previstas | D59: Ticket | E59: =$D$58*E11 -> 1.04 | F59: =$D$58*F11 -> 1.248 | G59: =$D$58*G11 -> 1.664 | H59: =$D$58*H11 -> 1.8304 | I59: =$D$58*I11 -> 1.9968 | J59: =$D$58*J11 -> 2.1632 | K59: =$D$58*K11 -> 2.3296 | L59: =$D$58*L11 -> 2.496 | ... S59: =$D$58*S11 -> 0
A60: Faturamento previsto | B60: Faturamento total | C60: =SUM(E60:P60) -> 461413.33 | D60: =B58/C58 -> 18333.333 | E60: =E59*$D$60 -> 19066.667 | F60: =F59*$D$60 -> 22880 | G60: =G59*$D$60 -> 30506.667 | H60: =H59*$D$60 -> 33557.333 | I60: =I59*$D$60 -> 36608 | J60: =J59*$D$60 -> 39658.667 | K60: =K59*$D$60 -> 42709.333 | L60: =L59*$D$60 -> 45760 | ... S60: =S59*$D$60 -> 0
A61: Parcela 1 | E61: =E60/4 -> 4766.6667 | F61: =F60/4 -> 5720 | G61: =G60/4 -> 7626.6667 | H61: =H60/4 -> 8389.3333 | I61: =I60/4 -> 9152 | J61: =J60/4 -> 9914.6667 | K61: =K60/4 -> 10677.333 | L61: =L60/4 -> 11440 | ... S61: =S60/4 -> 0
A62: Parcela 2 | F62: =E61 -> 4766.6667 | G62: =F61 -> 5720 | H62: =G61 -> 7626.6667 | I62: =H61 -> 8389.3333 | J62: =I61 -> 9152 | K62: =J61 -> 9914.6667 | L62: =K61 -> 10677.333 | M62: =L61 -> 11440 | ... S62: =R61 -> 0
A63: Parcela 3 | G63: =F62 -> 4766.6667 | H63: =G62 -> 5720 | I63: =H62 -> 7626.6667 | J63: =I62 -> 8389.3333 | K63: =J62 -> 9152 | L63: =K62 -> 9914.6667 | M63: =L62 -> 10677.333 | N63: =M62 -> 11440 | ... S63: =R62 -> 0
A64: Parcela 4 | H64: =G63 -> 4766.6667 | I64: =H63 -> 5720 | J64: =I63 -> 7626.6667 | K64: =J63 -> 8389.3333 | L64: =K63 -> 9152 | M64: =L63 -> 9914.6667 | N64: =M63 -> 10677.333 | O64: =N63 -> 11440 | ... S64: =R63 -> 11440
A65: Total Recebido | E65: =SUM(E61:E64) -> 4766.6667 | F65: =SUM(F61:F64) -> 10486.667 | G65: =SUM(G61:G64) -> 18113.333 | H65: =SUM(H61:H64) -> 26502.667 | I65: =SUM(I61:I64) -> 30888 | J65: =SUM(J61:J64) -> 35082.667 | K65: =SUM(K61:K64) -> 38133.333 | L65: =SUM(L61:L64) -> 41184 | ... S65: =SUM(S61:S64) -> 11440
A66: Custo Inicial | D66: 0.45 | E66: =E60*$D$66 -> 8580 | F66: =F60*$D$66 -> 10296 | G66: =G60*$D$66 -> 13728 | H66: =H60*$D$66 -> 15100.8 | I66: =I60*$D$66 -> 16473.6 | J66: =J60*$D$66 -> 17846.4 | K66: =K60*$D$66 -> 19219.2 | L66: =L60*$D$66 -> 20592 | ... S66: =S60*$D$66 -> 0
A67: Saldo Real (caixa disponivel) | E67: =E65-E66 -> -3813.3333 | F67: =F65-F66 -> 190.66667 | G67: =G65-G66 -> 4385.3333 | H67: =H65-H66 -> 11401.867 | I67: =I65-I66 -> 14414.4 | J67: =J65-J66 -> 17236.267 | K67: =K65-K66 -> 18914.133 | L67: =L65-L66 -> 20592 | ... S67: =S65-S66 -> 11440
A68: Saldo Acumulado | B68: Receita total | C68: =P68 -> 183993.33 | E68: =E67 -> -3813.3333 | F68: =F67+E68 -> -3622.6667 | G68: =G67+F68 -> 762.66667 | H68: =H67+G68 -> 12164.533 | I68: =I67+H68 -> 26578.933 | J68: =J67+I68 -> 43815.2 | K68: =K67+J68 -> 62729.333 | L68: =L67+K68 -> 83321.333 | M68: =M67+L68 -> 105591.2 | ... S68: =S67+R68 -> 253777.33
A69: Lucro Real | D69: 0.35 | H69: =$D$69*E60 -> 6673.3333 | I69: =$D$69*F60 -> 8008 | J69: =$D$69*G60 -> 10677.333 | K69: =$D$69*H60 -> 11745.067 | L69: =$D$69*I60 -> 12812.8 | M69: =$D$69*J60 -> 13880.533 | N69: =$D$69*K60 -> 14948.267 | O69: =$D$69*L60 -> 16016 | ... S69: =$D$69*P60 -> 16016
A70: Margem Contribuição Obras | D70: 0.35 | E70: =E60*$D$70 -> 6673.3333 | F70: =F60*$D$70 -> 8008 | G70: =G60*$D$70 -> 10677.333 | H70: =H60*$D$70 -> 11745.067 | I70: =I60*$D$70 -> 12812.8 | J70: =J60*$D$70 -> 13880.533 | K70: =K60*$D$70 -> 14948.267 | L70: =L60*$D$70 -> 16016 | ... S70: =S60*$D$70 -> 0
A72: Faturamento Total Global | B72: =SUM(E72:P72) -> 3436152.6 | C72: média | D72: =AVERAGE(E72:P72) -> 286346.05 | E72: =E60+E78 -> 175525.12 | F72: =F60+F78 -> 174106.63 | G72: =G60+G78 -> 195579.31 | H72: =H60+H78 -> 205710.63 | I72: =I60+I78 -> 225804.8 | J72: =J60+J78 -> 277531.73 | K72: =K60+K78 -> 306429.87 | L72: =L60+L78 -> 337299.2 | ... P72: =P60+P78 -> 389459.2
C77: Total | D77: Média
A78: Fatutamento XPE Global | C78: =SUM(E78:P78) -> 2974739.3 | D78: =AVERAGE(E78:P78) -> 247894.94 | E78: =E52+E60+E25 -> 156458.45 | F78: =F52+F60+F25 -> 151226.63 | G78: =G52+G60+G25 -> 165072.65 | H78: =H52+H60+H25 -> 172153.3 | I78: =I52+I60+I25 -> 189196.8 | J78: =J52+J60+J25 -> 237873.07 | K78: =K52+K60+K25 -> 263720.53 | L78: =L52+L60+L25 -> 291539.2 | ... P78: =P52+P60+P25 -> 343699.2
A79: Margem LL XPE Global | B79: =C79/C78 -> 0.23388813 | C79: =SUM(E79:P79) -> 695756.22 | D79: =AVERAGE(E79:P79) -> 57979.685 | E79: =E69+E53+E26-E27 -> 5421.908 | F79: =F69+F53+F26-F27 -> -186.092 | G79: =G69+G53+G26-G27 -> 3669.908 | H79: =H69+H53+H26-H27 -> 12878.441 | I79: =I69+I53+I26-I27 -> 22928.6 | J79: =J69+J53+J26-J27 -> 51459.693 | K79: =K69+K53+K26-K27 -> 66544.707 | L79: =L69+L53+L26-L27 -> 82857.24 | ... P79: =P69+P53+P26-P27 -> 119803.37
A80: CONTRATO FECHADO - Consult. + Obras | C80: =SUM(E80:P80) -> 2591346.9 | D80: =AVERAGE(E80:P80) -> 215945.58 | E80: =E13+E60 -> 82440.267 | F80: =F13+F60 -> 109280 | G80: =G13+G60 -> 145706.67 | H80: =H13+H60 -> 174357.33 | I80: =I13+I60 -> 190208 | J80: =J13+J60 -> 222698.67 | K80: =K13+K60 -> 239829.33 | L80: =L13+L60 -> 276160 | ... P80: =P13+P60 -> 276160
E81: =SUM(E80:G80) -> 337426.93 | H81: =SUM(H80:J80) -> 587264 | K81: =SUM(K80:M80) -> 810560 | N81: =SUM(N80:P80) -> 856096

Sheet Máquina de Indicações
A1: Insights e Estudos dos Livros: | B1: Máquina de Indicações e Sistema de indicações sem fim | G1: CRM de Sucesso do cliente | L1: Notas de Quantificações, problemas de percepção de valor
G2: Quais campos preciso ter, onde vamos colher | L2: Percepção de valor do cronograma, mostrar que está indo antes,
A3: Pilares estratégico | B3: Conhecer | C3: Gostar | D3: Confiar | G3: Rotinas para cuidar disso | L3: Mapear os principais pontos de experiência
B4: Primeiro você conhece, depois você gosta e depois você confia | G4: Saber quais indicações vieram de onde
B5: Tráfego pago | C5: Não tá claro | D5: Apresentação e Entrega excelente | G5: Ranking dos indicadores e premiar isso...
C6: *Verdade e propósito
B7: Trabalhar em cima da autenticidade e segurança
A9: Qual nosso diferencial falável central | B9: " Procurar o que fernando falou (audrey) e trabalhar na ideia"
A10: Capacitação + Storytelling desse diferencial falável (evangelizar)
H12: =3000*24 -> 72000
A13: Diretrizes
A14: Colheita ativa de indicações alinhada a troca de valor
A15: Conteúdo utilizado como ferramenta de captação
A16: A empresa deve ser tão notável que os cliente se sentem compelidos a falar sobre
A20: Fases da Máquina de ciclo contínuo (1 a 4) | B20: Objetivos
A21: Marketing e vendas | B21: Gerar conteúdo como ferramenta de captação
A22: Vendas | B22: Colocar a indicação como expectativa e condição no momento da venda (Método do livro = Gustavo)
A23: Projetos e sucesso | B23: Entregar uma experiência consistente e quantificar os resultados
A24: Sucesso e marketing | B24: Reforçar os resultados, coletar feedbacks e indicações e nutrir os clientes promotores
A27: obs: É necessário quantificar o valor entregue... É necessário sempre mostrar que o valor entregue é muito maior do que o preço. Nunca é documentos é o sentimento de problema resolvido
A28: Mentalidade -> Dar para receber... Sempre focar em entregar
A30: Frases gatílho -> Reclamações que o cliente demonstra que precisa de você.
A31: Se parece que tudo que eu estou entregando é o básico, o que é o surpreendente. Ancoragem de percepção de valor. Overdelivery. Wow
A33: Objeções de indicação (sentimento de emprestar uma confiança depositada no pessoal).
A34: Fazer conexões com lógica e emoção (cérebro e coração)
A36: Faça perguntas abertas que obrigatoriamente gerem respostas positivas (para gerar conexão) - Ter a top list 10
A37: Confiança = Manter a promessa + Qualidade + Autenticidade
A38: Entusiasme encante ou surpreenda. Nosso diferencial está claro em nossas cabeças; Não entregar nosso diferencial como se fosse básico. É mágico!
A40: Medidores próprios com tecnologia embarcada
A41: Medir em todos os pontos
A42: Quantidade de equipamentos, medidores e tecnologias disponíveis e direcionados só para isso
... A52: Participar dos eventos e agendas das outras administradoras -> Pagar para falar nos Workshops
A53: Fazer e colher boas perguntas e formas de agregar, trocar ideias com outros, conseguir indicações de bons relacionamentos e ir atrás disso, retribuindo e fazendo parcerias estratégicas que fazem sentido. | M53: fly wheel indicações
A54: 1. Garantir q todas etapas são impecaveis
A55: 2. Cartas a mão de agradecimentos
A56: 3. Dedicar tempo para treinar os parceiros
A57: 4. Investir tempo em se relacionar com jornalistas
A59: Salvar o instagram e seguir na hora, valorizar em publico os insights das postagens, marcar depois os arrobas e salvar no CRM
A61: No onboard da plataforma posso entregar um overdelivery e também posso no processo de onboard de documentação saber quais documentos o cliente não tem atualizado e precisa gerir, tirar etc. Deixar os campos com os documentos só faltando adicionar por exemplo: Regimento interno, AVBC, Láudo SPDA, Láudo Instalações Elétricas, Estudo de disponibilidade de carga, projeto elétrico... etc... prever e dar outros slots... e com isso certificar o sindico especialista elétrico e o prédio que tem tudo em dia.... Usar o hooked.
